Nibbler/uP.v
//-----------------------------------
// Ricardo Pellecer Orellana
// Carné: 19072
// 22/Noviembre/2020
// -----------------------------------

//Program Counter - Sí funciona
module Counter (input wire clock, reset, load, enable, input wire [11:0]load_data, output reg [11:0]value);
  always @ (posedge clock, posedge reset) begin
    if (reset) begin
      value <= 12'b0;
    end
    else if (load) begin
      value <= load_data;
    end
    else if (enable) begin
      value <= value + 1;
    end
  end
endmodule

//ROM - Sí funciona
module ROM_Memory (input wire [11:0]address, output wire [7:0]opcode);
  reg [7:0] ROM [0:4095];
  initial begin
      $readmemh("instructions.list", ROM);
  end
  assign opcode = ROM[address];
endmodule

// Flip Flop Tipo D --> para fetch - Sí funciona
module flip_flop8 (input wire clk, reset, enable, input wire [7:0]d, output reg [7:0]q);
	always @ (posedge clk or posedge reset or enable)begin
		if (reset) begin
			q <= 8'b0;
		end
    else if (enable) begin
      q <= d;
    end
	end
endmodule

//Fetch - Sí funciona
module Fetch (input wire clk, reset, enable, input wire [7:0]opcode, output wire [3:0]instruction, operand);
  wire [7:0]q;
  assign instruction = q[7:4];
  assign operand = q[3:0];
  flip_flop8 F1(clk, reset, enable, opcode, q);
endmodule

// Flip Flop Tipo D --> para flags - Sí funciona
module Flags (input wire clk, reset, enable, input wire [1:0]d, output reg [1:0]q);
	always @ (posedge clk or posedge reset or enable)begin
		if (reset) begin
			q <= 2'b0;
		end
    else if (enable) begin
      q <= d;
    end
	end
endmodule

// Flip Flop Tipo D --> para toggle del phase - Sí funciona
module flip_flop1 (input wire clk, reset, enable, input wire d, output reg q);
	always @ (posedge clk or posedge reset or enable)begin
		if (reset) begin
			q <= 1'b0;
		end
    else if (enable) begin
      q <= d;
    end
	end
endmodule

// Flip Flop Toggle --> para phase - Sí funciona
module Phase (input wire clk, reset, enable, output wire q);
  wire d;
  assign d = ~q;
	flip_flop1 F1(clk, reset, enable, d, q);
endmodule

//Decode - Sí funciona
module Microcode(input wire [6:0]address, output reg [12:0]control);
  always @ (address) begin
    casex (address)
    7'bxxxxxx0: //0
      control <= 13'b1000000001000;
    7'b00001x1: //1
      control <= 13'b0100000001000;
    7'b00000x1: //2
      control <= 13'b1000000001000;
    7'b00011x1: //3
      control <= 13'b1000000001000;
    7'b00010x1: //4
      control <= 13'b0100000001000;
    7'b0010xx1: //5
      control <= 13'b0001001000010;
    7'b0011xx1: //6
      control <= 13'b1001001100000;
    7'b0100xx1: //7
      control <= 13'b0011010000010;
    7'b0101xx1: //8
      control <= 13'b0011010000100;
    7'b0110xx1: //9
      control <= 13'b1011010100000;
    7'b0111xx1: //10
      control <= 13'b1000000111000;
    7'b1000x11: //11
      control <= 13'b0100000001000;
    7'b1000x01: //12
      control <= 13'b1000000001000;
    7'b1001x11: //13
      control <= 13'b1000000001000;
    7'b1001x01: //14
      control <= 13'b0100000001000;
    7'b1010xx1: //15
      control <= 13'b0011011000010;
    7'b1011xx1: //16
      control <= 13'b1011011100000;
    7'b1100xx1: //17
      control <= 13'b0100000001000;
    7'b1101xx1: //18
      control <= 13'b0000000001001;
    7'b1110xx1: //19
      control <= 13'b0011100000010;
    7'b1111xx1: //20
      control <= 13'b1011100100000;
    default:
      control <= 13'b1111111111111;
    endcase
  end
endmodule

// Buffer Tri-estado - Sí funciona
module Tris (input wire enable, input wire [3:0]in, output wire [3:0]out);
  assign out = enable ? in:4'bz;
endmodule

//RAM - Sí funciona
module RAM_Memory (input wire enable, write, read, input wire [11:0]address_RAM, inout [3:0]data);
  reg [3:0] RAM [0:4095];
  reg [3:0]data_out;

  //Coloca un tris para poder escribir o leer
  assign data = (enable & read & ~write) ? data_out:4'bz;
  //Bloque de escritura
  always @ ( address_RAM or data or enable or write ) begin
    if (enable && write) begin
      RAM[address_RAM] = data;
    end
  end
  //Bloque de lectura
  always @ ( address_RAM or enable or write or read) begin
    if (enable && ~write && read) begin
      data_out = RAM[address_RAM];
    end
  end
endmodule

// Flip Flop Tipo D - Sí funciona
module Accumulator (input wire clk, reset, enable, input wire [3:0]result, output reg [3:0]accu);
	always @ (posedge clk or posedge reset or enable) begin
		if (reset) begin
			accu <= 4'b0;
		end
    else if (enable) begin
      accu <= result;
    end
	end
endmodule

//ALU - Los 3 bits de seleccion vienen del microcode el databus es el operand y la accu es W - Sí funciona
module ALU (input wire [3:0]data_bus, accu, input wire [2:0]selector, output reg [3:0]result, output wire [1:0]flags);
  wire zero;
  reg carry;
  always @ ( * ) begin
    case (selector)
    0:
      {carry, result} <= accu;
    1:
      {carry, result} <= accu - data_bus;
    2:
      {carry, result} <= data_bus;
    3:
      {carry, result} <= accu + data_bus;
    4:
      {carry, result} <= {1'b0, ~(accu & data_bus)};
    default:
      {carry, result} <= 5'b0;
    endcase
  end
  assign zero = (result == 4'b0) ? 1'b1:1'b0;
  assign flags[0] = zero;
  assign flags[1] = carry;
endmodule

// Flip Flop Tipo D --> para outputs - Sí funciona
module Outputs (input wire clk, reset, enable, input wire [3:0]d, output reg [3:0]q);
	always @ (posedge clk or posedge reset or enable)begin
		if (reset) begin
			q <= 4'b0;
		end
    else if (enable) begin
      q <= d;
    end
	end
endmodule

//Nibbler - Sí funciona
module uP (input wire clock, reset, input wire [3:0]pushbuttons, output wire phase, c_flag, z_flag, output wire [3:0]instr, oprnd, data_bus, FF_out, accu, output wire [7:0]program_byte, output wire [11:0]PC, address_RAM);
  //Cables internos del Nibbler
  wire [1:0]flags_in, flags_out; //posicion 1 es carry y 0 es zero
  wire [12:0]control;
  wire [3:0]alu_result;
  wire [6:0]address;
  //Defino a address como la contatenacion de varias entradas
  assign address = {instr, c_flag, z_flag, phase};
  //address_RAM
  assign address_RAM = {oprnd, program_byte};
  //Defino mis banderas concatenadas
  assign c_flag = flags_out[1];
  assign z_flag = flags_out[0];
  //Defino a los bits de control con mi address a traves del decode
  Microcode M1(address, control);
  //Doy valor al PC a traves de las señales de control 11 y 12 -load y enable respectivamente-
  Counter PC1(clock, reset, control[11], control[12], address_RAM, PC);
  //Busco la instruccion correspondiente en la ROM con el PC
  ROM_Memory ROM1(PC, program_byte);
  //Fetch divide al program_byte -opcode- en instruccion y operando
  Fetch FE1(clock, reset, ~phase, program_byte, instr, oprnd);
  //Uso el toggle para definir el phase
  Phase PH1(clock, reset, 1'b1, phase); //Enable del phase siempre en 1?????
  //Dejo pasar mis banderas con el bit 9 de control -LoadFlags-
  Flags FL1(clock, reset, control[9], flags_in, flags_out);
  //Primer Bus Driver - Defino a data_bus usando el bit 1 de control -oeOprnd-
  Tris BD1(control[1], oprnd, data_bus);
  //Operaciones con ALU entra data_bus y accu, selecciono con los bits 6, 7 y 8 de control, sale el resultado y las banderas
  ALU A1(data_bus, accu, control[8:6], alu_result, flags_in);
  //Genero el registro W - Defino a accu a traves del resultado de la ALU y del bit 10 de control -loadA-
  Accumulator A2(clock, reset, control[10], alu_result, accu);
  //Segundo Bus Driver - Defino a data_bus usando el bit 3 de control -oeALU-
  Tris BD2(control[3], alu_result, data_bus);
  //Definicion de la RAM uso de control 4 y 5 -weRAM y csRAM respectivamente-
  RAM_Memory RAM1(control[5], control[4], control[5], address_RAM, data_bus); //output enable de la RAM es cuando los otros tres tris estan en cero????
  //Tercer Bus Driver - Defino a data_bus usando el bit 2 de control -oeIN-
  Tris BD3(control[2], pushbuttons, data_bus);
  //Flip flop para Outputs con bit 0 de control -loadOut-
  Outputs O1(clock, reset, control[0], data_bus, FF_out);
endmodule

Nibbler/uP_tb.v
module testbench();
  //Variables de entrada
  reg clock, reset;
  reg [3:0]pushbuttons;

  //Variables de salida
  wire phase, c_flag, z_flag;
  wire [3:0]instr, oprnd, data_bus, FF_out, accu;
  wire [7:0]program_byte;
  wire [11:0]pc, address_ram;
  //Instanciaciones
  uP MicroProcessor(clock, reset, pushbuttons, phase, c_flag, z_flag, instr, oprnd, data_bus, FF_out, accu, program_byte, pc, address_ram);

  always
    #5 clock <=~clock;

    //Ejercicio 1
    initial begin
    #2
    $display(" \nNibbler ");
    $display("clock reset pushbuttons |  phase  c_flag   z_flag   instr   oprnd   data_bus  FF_out   Accu   program_byte       PC          address_ram ");
    $display("------------------------|----------------------------------------------------------------------------------------------------------------");
    $monitor("%b       %b       %b    |   %b       %b        %b      %b    %b     %b      %b    %b     %b     %b    %b ", clock, reset, pushbuttons, phase, c_flag, z_flag, instr, oprnd, data_bus, FF_out, accu, program_byte, pc, address_ram);

      reset = 1; clock = 0; pushbuttons = 4'b0;
  #1  reset = 0; pushbuttons = 4'b1010;
    end

    initial
      #640 $finish;
    initial begin
        $dumpfile("uP_tb.vcd");
        $dumpvars(0, testbench);
      end
  endmodule

Nibbler/uP_tb.vcd
$date
	Fri Nov 20 19:00:19 2020
$end
$version
	Icarus Verilog
$end
$timescale
	1ps
$end
$scope module testbench $end
$var wire 4 ! data_bus [3:0] $end
$var wire 1 " z_flag $end
$var wire 8 # program_byte [7:0] $end
$var wire 1 $ phase $end
$var wire 12 % pc [11:0] $end
$var wire 4 & oprnd [3:0] $end
$var wire 4 ' instr [3:0] $end
$var wire 1 ( c_flag $end
$var wire 12 ) address_ram [11:0] $end
$var wire 4 * accu [3:0] $end
$var wire 4 + FF_out [3:0] $end
$var reg 1 , clock $end
$var reg 4 - pushbuttons [3:0] $end
$var reg 1 . reset $end
$scope module MicroProcessor $end
$var wire 1 , clock $end
$var wire 4 / data_bus [3:0] $end
$var wire 4 0 pushbuttons [3:0] $end
$var wire 1 . reset $end
$var wire 1 " z_flag $end
$var wire 8 1 program_byte [7:0] $end
$var wire 1 $ phase $end
$var wire 4 2 oprnd [3:0] $end
$var wire 4 3 instr [3:0] $end
$var wire 2 4 flags_out [1:0] $end
$var wire 2 5 flags_in [1:0] $end
$var wire 13 6 control [12:0] $end
$var wire 1 ( c_flag $end
$var wire 4 7 alu_result [3:0] $end
$var wire 12 8 address_RAM [11:0] $end
$var wire 7 9 address [6:0] $end
$var wire 4 : accu [3:0] $end
$var wire 12 ; PC [11:0] $end
$var wire 4 < FF_out [3:0] $end
$scope module A1 $end
$var wire 4 = data_bus [3:0] $end
$var wire 3 > selector [2:0] $end
$var wire 1 ? zero $end
$var wire 2 @ flags [1:0] $end
$var wire 4 A accu [3:0] $end
$var reg 1 B carry $end
$var reg 4 C result [3:0] $end
$upscope $end
$scope module A2 $end
$var wire 1 , clk $end
$var wire 1 D enable $end
$var wire 1 . reset $end
$var wire 4 E result [3:0] $end
$var reg 4 F accu [3:0] $end
$upscope $end
$scope module BD1 $end
$var wire 1 G enable $end
$var wire 4 H out [3:0] $end
$var wire 4 I in [3:0] $end
$upscope $end
$scope module BD2 $end
$var wire 1 J enable $end
$var wire 4 K in [3:0] $end
$var wire 4 L out [3:0] $end
$upscope $end
$scope module BD3 $end
$var wire 1 M enable $end
$var wire 4 N in [3:0] $end
$var wire 4 O out [3:0] $end
$upscope $end
$scope module FE1 $end
$var wire 1 , clk $end
$var wire 1 P enable $end
$var wire 1 . reset $end
$var wire 8 Q q [7:0] $end
$var wire 4 R operand [3:0] $end
$var wire 8 S opcode [7:0] $end
$var wire 4 T instruction [3:0] $end
$scope module F1 $end
$var wire 1 , clk $end
$var wire 1 P enable $end
$var wire 1 . reset $end
$var wire 8 U d [7:0] $end
$var reg 8 V q [7:0] $end
$upscope $end
$upscope $end
$scope module FL1 $end
$var wire 1 , clk $end
$var wire 2 W d [1:0] $end
$var wire 1 X enable $end
$var wire 1 . reset $end
$var reg 2 Y q [1:0] $end
$upscope $end
$scope module M1 $end
$var wire 7 Z address [6:0] $end
$var reg 13 [ control [12:0] $end
$upscope $end
$scope module O1 $end
$var wire 1 , clk $end
$var wire 4 \ d [3:0] $end
$var wire 1 ] enable $end
$var wire 1 . reset $end
$var reg 4 ^ q [3:0] $end
$upscope $end
$scope module PC1 $end
$var wire 1 , clock $end
$var wire 1 _ enable $end
$var wire 1 ` load $end
$var wire 12 a load_data [11:0] $end
$var wire 1 . reset $end
$var reg 12 b value [11:0] $end
$upscope $end
$scope module PH1 $end
$var wire 1 , clk $end
$var wire 1 c d $end
$var wire 1 d enable $end
$var wire 1 . reset $end
$var wire 1 $ q $end
$scope module F1 $end
$var wire 1 , clk $end
$var wire 1 c d $end
$var wire 1 d enable $end
$var wire 1 . reset $end
$var reg 1 $ q $end
$upscope $end
$upscope $end
$scope module RAM1 $end
$var wire 12 e address_RAM [11:0] $end
$var wire 4 f data [3:0] $end
$var wire 1 g enable $end
$var wire 1 h read $end
$var wire 1 i write $end
$var reg 4 j data_out [3:0] $end
$upscope $end
$scope module ROM1 $end
$var wire 12 k address [11:0] $end
$var wire 8 l opcode [7:0] $end
$upscope $end
$upscope $end
$upscope $end
$enddefinitions $end
#0
$dumpvars
bx l
bx k
bx j
xi
xh
xg
bx f
bx e
1d
xc
bx b
bx a
x`
x_
bx ^
x]
bx \
bx [
bx Z
bx Y
xX
bx W
bx V
bx U
bx T
bx S
bx R
bx Q
xP
bx O
bx N
xM
bx L
bx K
xJ
bx I
bx H
xG
bx F
bx E
xD
bx C
xB
bx A
bx @
x?
bx >
bx =
bx <
bx ;
bx :
bx 9
bx 8
bx 7
bx 6
bx 5
bx 4
bx 3
bx 2
bx 1
bx 0
bx /
x.
bx -
x,
bx +
bx *
bx )
x(
bx '
bx &
bx %
x$
bx #
x"
bx !
$end
#2
b0 !
b0 /
b0 =
b0 H
b0 L
b0 O
b0 \
b0 f
1?
0]
0M
0h
0i
0g
1J
0D
b0 >
0G
0X
1_
0`
b1 5
b1 @
b1 W
0B
b0 7
b0 C
b0 E
b0 K
b1000000001000 6
b1000000001000 [
b0 &
b0 2
b0 I
b0 R
b0 '
b0 3
b0 T
0"
0(
1c
1P
b0 *
b0 :
b0 A
b0 F
b0 Q
b0 V
b0 4
b0 Y
b0 +
b0 <
b0 ^
b1001010 )
b1001010 8
b1001010 a
b1001010 e
b1001010 #
b1001010 1
b1001010 S
b1001010 U
b1001010 l
b0 %
b0 ;
b0 b
b0 k
b0 9
b0 Z
0$
b0 -
b0 0
b0 N
0,
1.
#3
b1010 -
b1010 0
b1010 N
0.
#5
b0 5
b0 @
b0 W
0?
1"
b1010 7
b1010 C
b1010 E
b1010 K
b1 4
b1 Y
b1010 !
b1010 /
b1010 =
b1010 H
b1010 L
b1010 O
b1010 \
b1010 f
0J
1D
b10 >
1G
1X
0_
b11010000010 6
b11010000010 [
b1010 &
b1010 2
b1010 I
b1010 R
b100 '
b100 3
b100 T
0c
0P
b1001010 Q
b1001010 V
b101010100101 )
b101010100101 8
b101010100101 a
b101010100101 e
b10100101 #
b10100101 1
b10100101 S
b10100101 U
b10100101 l
b1 %
b1 ;
b1 b
b1 k
b100011 9
b100011 Z
1$
1,
#10
0,
#15
b1010 !
b1010 /
b1010 =
b1010 H
b1010 L
b1010 O
b1010 \
b1010 f
b10110100101 )
b10110100101 8
b10110100101 a
b10110100101 e
b101 &
b101 2
b101 I
b101 R
b1010 '
b1010 3
b1010 T
1J
0D
b0 >
0G
0X
1_
b10100101 Q
b10100101 V
b1000000001000 6
b1000000001000 [
0"
1c
1P
b1010 *
b1010 :
b1010 A
b1010 F
b0 4
b0 Y
b1010000 9
b1010000 Z
0$
1,
#20
0,
#25
b0 5
b0 @
b0 W
0B
b1111 7
b1111 C
b1111 E
b1111 K
b101 !
b101 /
b101 =
b101 H
b101 L
b101 O
b101 \
b101 f
0J
1D
b11 >
1G
1X
0_
b11011000010 6
b11011000010 [
0c
0P
b10100101111 )
b10100101111 8
b10100101111 a
b10100101111 e
b101111 #
b101111 1
b101111 S
b101111 U
b101111 l
b10 %
b10 ;
b10 b
b10 k
b1010001 9
b1010001 Z
1$
1,
#30
0,
#35
b1111 !
b1111 /
b1111 =
b1111 H
b1111 L
b1111 O
b1111 \
b1111 f
b111100101111 )
b111100101111 8
b111100101111 a
b111100101111 e
b1111 &
b1111 2
b1111 I
b1111 R
b10 '
b10 3
b10 T
1J
0D
b0 >
0G
0X
1_
b101111 Q
b101111 V
b0 5
b0 @
b0 W
0B
b1111 7
b1111 C
b1111 E
b1111 K
b1000000001000 6
b1000000001000 [
1c
1P
b1111 *
b1111 :
b1111 A
b1111 F
b10000 9
b10000 Z
0$
1,
#40
0,
#45
b1 5
b1 @
b1 W
1?
b0 7
b0 C
b0 E
b0 K
0J
b1 >
1G
1X
0_
b1001000010 6
b1001000010 [
0c
0P
b111111010100 )
b111111010100 8
b111111010100 a
b111111010100 e
b11010100 #
b11010100 1
b11010100 S
b11010100 U
b11010100 l
b11 %
b11 ;
b11 b
b11 k
b10001 9
b10001 Z
1$
1,
#50
0,
#55
b0 5
b0 @
b0 W
0?
b1111 7
b1111 C
b1111 E
b1111 K
b1111 !
b1111 /
b1111 =
b1111 H
b1111 L
b1111 O
b1111 \
b1111 f
b10011010100 )
b10011010100 8
b10011010100 a
b10011010100 e
b100 &
b100 2
b100 I
b100 R
b1101 '
b1101 3
b1101 T
1J
b0 >
0G
0X
1_
b11010100 Q
b11010100 V
b1000000001000 6
b1000000001000 [
1"
1c
1P
b1 4
b1 Y
b1101010 9
b1101010 Z
0$
1,
#60
0,
#65
b1111 +
b1111 <
b1111 ^
1]
0_
b1001 6
b1001 [
0c
0P
b10001010111 )
b10001010111 8
b10001010111 a
b10001010111 e
b1010111 #
b1010111 1
b1010111 S
b1010111 U
b1010111 l
b100 %
b100 ;
b100 b
b100 k
b1101011 9
b1101011 Z
1$
1,
#70
0,
#75
b11101010111 )
b11101010111 8
b11101010111 a
b11101010111 e
b111 &
b111 2
b111 I
b111 R
b101 '
b101 3
b101 T
0]
1_
b1010111 Q
b1010111 V
b1000000001000 6
b1000000001000 [
1c
1P
b101010 9
b101010 Z
0$
1,
#80
0,
#85
0"
b1010 7
b1010 C
b1010 E
b1010 K
b0 4
b0 Y
b1010 !
b1010 /
b1010 =
b1010 H
b1010 L
b1010 O
b1010 \
b1010 f
1M
0J
1D
b10 >
1X
0_
b11010000100 6
b11010000100 [
0c
0P
b11111101010 )
b11111101010 8
b11111101010 a
b11111101010 e
b11101010 #
b11101010 1
b11101010 S
b11101010 U
b11101010 l
b101 %
b101 ;
b101 b
b101 k
b101001 9
b101001 Z
1$
1,
#90
0,
#95
b101011101010 )
b101011101010 8
b101011101010 a
b101011101010 e
b1010 &
b1010 2
b1010 I
b1010 R
b1110 '
b1110 3
b1110 T
0M
1J
0D
b0 >
0X
1_
b11101010 Q
b11101010 V
b1000000001000 6
b1000000001000 [
1c
1P
b1010 *
b1010 :
b1010 A
b1010 F
b1110000 9
b1110000 Z
0$
1,
#100
0,
#105
b101 7
b101 C
b101 E
b101 K
0J
1D
b100 >
1G
1X
0_
b11100000010 6
b11100000010 [
0c
0P
b101001001111 )
b101001001111 8
b101001001111 a
b101001001111 e
b1001111 #
b1001111 1
b1001111 S
b1001111 U
b1001111 l
b110 %
b110 ;
b110 b
b110 k
b1110001 9
b1110001 Z
1$
1,
#110
0,
#115
b101 !
b101 /
b101 =
b101 H
b101 L
b101 O
b101 \
b101 f
b111101001111 )
b111101001111 8
b111101001111 a
b111101001111 e
b1111 &
b1111 2
b1111 I
b1111 R
b100 '
b100 3
b100 T
1J
0D
b0 >
0G
0X
1_
b1001111 Q
b1001111 V
b101 7
b101 C
b101 E
b101 K
b1000000001000 6
b1000000001000 [
1c
1P
b101 *
b101 :
b101 A
b101 F
b100000 9
b100000 Z
0$
1,
#120
0,
#125
b1111 7
b1111 C
b1111 E
b1111 K
b1111 !
b1111 /
b1111 =
b1111 H
b1111 L
b1111 O
b1111 \
b1111 f
0J
1D
b10 >
1G
1X
0_
b11010000010 6
b11010000010 [
0c
0P
b111101110000 )
b111101110000 8
b111101110000 a
b111101110000 e
b1110000 #
b1110000 1
b1110000 S
b1110000 U
b1110000 l
b111 %
b111 ;
b111 b
b111 k
b100001 9
b100001 Z
1$
1,
#130
0,
#135
b1111 !
b1111 /
b1111 =
b1111 H
b1111 L
b1111 O
b1111 \
b1111 f
b1110000 )
b1110000 8
b1110000 a
b1110000 e
b0 &
b0 2
b0 I
b0 R
b111 '
b111 3
b111 T
1J
0D
b0 >
0G
0X
1_
b1110000 Q
b1110000 V
b1000000001000 6
b1000000001000 [
1c
1P
b1111 *
b1111 :
b1111 A
b1111 F
b111000 9
b111000 Z
0$
1,
#140
0,
#145
1h
1i
1g
b1000000111000 6
b1000000111000 [
0c
0P
b0 )
b0 8
b0 a
b0 e
b0 #
b0 1
b0 S
b0 U
b0 l
b1000 %
b1000 ;
b1000 b
b1000 k
b111001 9
b111001 Z
1$
1,
#150
0,
#155
b110 '
b110 3
b110 T
0h
0i
0g
b1100000 Q
b1100000 V
b1000000001000 6
b1000000001000 [
1c
1P
b1100000 )
b1100000 8
b1100000 a
b1100000 e
b1100000 #
b1100000 1
b1100000 S
b1100000 U
b1100000 l
b1001 %
b1001 ;
b1001 b
b1001 k
b110000 9
b110000 Z
0$
1,
#160
0,
#165
b1111 7
b1111 C
b1111 E
b1111 K
b1111 j
b1111 !
b1111 /
b1111 =
b1111 H
b1111 L
b1111 O
b1111 \
b1111 f
1h
1g
0J
1D
b10 >
1X
b1011010100000 6
b1011010100000 [
0c
0P
b0 )
b0 8
b0 a
b0 e
b0 #
b0 1
b0 S
b0 U
b0 l
b1010 %
b1010 ;
b1010 b
b1010 k
b110001 9
b110001 Z
1$
1,
#170
0,
#175
b0 5
b0 @
b0 W
0?
b1 &
b1 2
b1 I
b1 R
b1010 '
b1010 3
b1010 T
0h
0g
1J
0D
b0 >
0X
b1111 7
b1111 C
b1111 E
b1111 K
b10100001 Q
b10100001 V
b1000000001000 6
b1000000001000 [
b1111 !
b1111 /
b1111 =
b1111 H
b1111 L
b1111 O
b1111 \
b1111 f
bx j
1c
1P
b110100001 )
b110100001 8
b110100001 a
b110100001 e
b10100001 #
b10100001 1
b10100001 S
b10100001 U
b10100001 l
b1011 %
b1011 ;
b1011 b
b1011 k
b1010000 9
b1010000 Z
0$
1,
#180
0,
#185
1?
b11 5
b11 @
b11 W
1B
b0 7
b0 C
b0 E
b0 K
b1 !
b1 /
b1 =
b1 H
b1 L
b1 O
b1 \
b1 f
0J
1D
b11 >
1G
1X
0_
b11011000010 6
b11011000010 [
0c
0P
b101000010 )
b101000010 8
b101000010 a
b101000010 e
b1000010 #
b1000010 1
b1000010 S
b1000010 U
b1000010 l
b1100 %
b1100 ;
b1100 b
b1100 k
b1010001 9
b1010001 Z
1$
1,
#190
0,
#195
b0 !
b0 /
b0 =
b0 H
b0 L
b0 O
b0 \
b0 f
b1001000010 )
b1001000010 8
b1001000010 a
b1001000010 e
b10 &
b10 2
b10 I
b10 R
b100 '
b100 3
b100 T
1?
1J
0D
b0 >
0G
0X
1_
b1000010 Q
b1000010 V
b1 5
b1 @
b1 W
0B
b0 7
b0 C
b0 E
b0 K
b1000000001000 6
b1000000001000 [
1"
1(
1c
1P
b0 *
b0 :
b0 A
b0 F
b11 4
b11 Y
b100110 9
b100110 Z
0$
1,
#200
0,
#205
b0 5
b0 @
b0 W
0?
0(
b10 7
b10 C
b10 E
b10 K
b1 4
b1 Y
b10 !
b10 /
b10 =
b10 H
b10 L
b10 O
b10 \
b10 f
0J
1D
b10 >
1G
1X
0_
b11010000010 6
b11010000010 [
0c
0P
b1011110000 )
b1011110000 8
b1011110000 a
b1011110000 e
b11110000 #
b11110000 1
b11110000 S
b11110000 U
b11110000 l
b1101 %
b1101 ;
b1101 b
b1101 k
b100011 9
b100011 Z
1$
1,
#210
0,
#215
b10 !
b10 /
b10 =
b10 H
b10 L
b10 O
b10 \
b10 f
b11110000 )
b11110000 8
b11110000 a
b11110000 e
b0 &
b0 2
b0 I
b0 R
b1111 '
b1111 3
b1111 T
1J
0D
b0 >
0G
0X
1_
b11110000 Q
b11110000 V
b1000000001000 6
b1000000001000 [
0"
1c
1P
b10 *
b10 :
b10 A
b10 F
b0 4
b0 Y
b1111000 9
b1111000 Z
0$
1,
#220
0,
#225
b1101 7
b1101 C
b1101 E
b1101 K
b1111 j
b1111 !
b1111 /
b1111 =
b1111 H
b1111 L
b1111 O
b1111 \
b1111 f
1h
1g
0J
1D
b100 >
1X
b1011100100000 6
b1011100100000 [
0c
0P
b0 )
b0 8
b0 a
b0 e
b0 #
b0 1
b0 S
b0 U
b0 l
b1110 %
b1110 ;
b1110 b
b1110 k
b1111001 9
b1111001 Z
1$
1,
#230
0,
#235
b1111 &
b1111 2
b1111 I
b1111 R
b100 '
b100 3
b100 T
0h
0g
1J
0D
b0 >
0X
b1001111 Q
b1001111 V
b1101 7
b1101 C
b1101 E
b1101 K
b1000000001000 6
b1000000001000 [
b1101 !
b1101 /
b1101 =
b1101 H
b1101 L
b1101 O
b1101 \
b1101 f
bx j
1c
1P
b1101 *
b1101 :
b1101 A
b1101 F
b111101001111 )
b111101001111 8
b111101001111 a
b111101001111 e
b1001111 #
b1001111 1
b1001111 S
b1001111 U
b1001111 l
b1111 %
b1111 ;
b1111 b
b1111 k
b100000 9
b100000 Z
0$
1,
#240
0,
#245
b1111 7
b1111 C
b1111 E
b1111 K
b1111 !
b1111 /
b1111 =
b1111 H
b1111 L
b1111 O
b1111 \
b1111 f
0J
1D
b10 >
1G
1X
0_
b11010000010 6
b11010000010 [
0c
0P
b111110110000 )
b111110110000 8
b111110110000 a
b111110110000 e
b10110000 #
b10110000 1
b10110000 S
b10110000 U
b10110000 l
b10000 %
b10000 ;
b10000 b
b10000 k
b100001 9
b100001 Z
1$
1,
#250
0,
#255
b1111 !
b1111 /
b1111 =
b1111 H
b1111 L
b1111 O
b1111 \
b1111 f
b10110000 )
b10110000 8
b10110000 a
b10110000 e
b0 &
b0 2
b0 I
b0 R
b1011 '
b1011 3
b1011 T
1J
0D
b0 >
0G
0X
1_
b10110000 Q
b10110000 V
b1000000001000 6
b1000000001000 [
1c
1P
b1111 *
b1111 :
b1111 A
b1111 F
b1011000 9
b1011000 Z
0$
1,
#260
0,
#265
b10 5
b10 @
b10 W
1B
b1110 7
b1110 C
b1110 E
b1110 K
b1111 j
b1111 !
b1111 /
b1111 =
b1111 H
b1111 L
b1111 O
b1111 \
b1111 f
1h
1g
0J
1D
b11 >
1X
b1011011100000 6
b1011011100000 [
0c
0P
b0 )
b0 8
b0 a
b0 e
b0 #
b0 1
b0 S
b0 U
b0 l
b10001 %
b10001 ;
b10001 b
b10001 k
b1011001 9
b1011001 Z
1$
1,
#270
0,
#275
0?
b1100 '
b1100 3
b1100 T
0h
0g
1J
0D
b0 >
0X
b0 5
b0 @
b0 W
0B
b11000000 Q
b11000000 V
b1110 7
b1110 C
b1110 E
b1110 K
b1000000001000 6
b1000000001000 [
b1110 !
b1110 /
b1110 =
b1110 H
b1110 L
b1110 O
b1110 \
b1110 f
1(
bx j
1c
1P
b1110 *
b1110 :
b1110 A
b1110 F
b10 4
b10 Y
b11000000 )
b11000000 8
b11000000 a
b11000000 e
b11000000 #
b11000000 1
b11000000 S
b11000000 U
b11000000 l
b10010 %
b10010 ;
b10010 b
b10010 k
b1100100 9
b1100100 Z
0$
1,
#280
0,
#285
0_
1`
b100000001000 6
b100000001000 [
0c
0P
b1000100 )
b1000100 8
b1000100 a
b1000100 e
b1000100 #
b1000100 1
b1000100 S
b1000100 U
b1000100 l
b10011 %
b10011 ;
b10011 b
b10011 k
b1100101 9
b1100101 Z
1$
1,
#290
0,
#295
b1 &
b1 2
b1 I
b1 R
b100 '
b100 3
b100 T
1_
0`
b1000001 Q
b1000001 V
b1000000001000 6
b1000000001000 [
1c
1P
b101000001 )
b101000001 8
b101000001 a
b101000001 e
b1000001 #
b1000001 1
b1000001 S
b1000001 U
b1000001 l
b1000100 %
b1000100 ;
b1000100 b
b1000100 k
b100100 9
b100100 Z
0$
1,
#300
0,
#305
0(
b1 7
b1 C
b1 E
b1 K
b0 4
b0 Y
b1 !
b1 /
b1 =
b1 H
b1 L
b1 O
b1 \
b1 f
0J
1D
b10 >
1G
1X
0_
b11010000010 6
b11010000010 [
0c
0P
b100100010 )
b100100010 8
b100100010 a
b100100010 e
b100010 #
b100010 1
b100010 S
b100010 U
b100010 l
b1000101 %
b1000101 ;
b1000101 b
b1000101 k
b100001 9
b100001 Z
1$
1,
#310
0,
#315
b1 !
b1 /
b1 =
b1 H
b1 L
b1 O
b1 \
b1 f
b1000100010 )
b1000100010 8
b1000100010 a
b1000100010 e
b10 &
b10 2
b10 I
b10 R
b10 '
b10 3
b10 T
1J
0D
b0 >
0G
0X
1_
b100010 Q
b100010 V
b1000000001000 6
b1000000001000 [
1c
1P
b1 *
b1 :
b1 A
b1 F
b10000 9
b10000 Z
0$
1,
#320
0,
#325
b10 5
b10 @
b10 W
1B
b1111 7
b1111 C
b1111 E
b1111 K
b10 !
b10 /
b10 =
b10 H
b10 L
b10 O
b10 \
b10 f
0J
b1 >
1G
1X
0_
b1001000010 6
b1001000010 [
0c
0P
b1000000000 )
b1000000000 8
b1000000000 a
b1000000000 e
b0 #
b0 1
b0 S
b0 U
b0 l
b1000110 %
b1000110 ;
b1000110 b
b1000110 k
b10001 9
b10001 Z
1$
1,
#330
0,
#335
b0 5
b0 @
b0 W
0B
b1 7
b1 C
b1 E
b1 K
b1 !
b1 /
b1 =
b1 H
b1 L
b1 O
b1 \
b1 f
b0 )
b0 8
b0 a
b0 e
b0 &
b0 2
b0 I
b0 R
b0 '
b0 3
b0 T
1J
b0 >
0G
0X
1_
b0 Q
b0 V
b1000000001000 6
b1000000001000 [
1(
1c
1P
b10 4
b10 Y
b100 9
b100 Z
0$
1,
#340
0,
