Nibbler/uP.v
//-----------------------------------
// Ricardo Pellecer Orellana
// Carné: 19072
// 22/Noviembre/2020
// -----------------------------------

//Program Counter - Sí funciona
module Counter (input wire clock, reset, load, enable, input wire [11:0]load_data, output reg [11:0]value);
  always @ (posedge clock, posedge reset, load, load_data) begin
    if (reset) begin
      value <= 12'b0;
    end
    else if (load) begin
      value <= load_data;
    end
    else if (enable) begin
      if (value < 12'b111111111111) begin
        value <= value + 1;
      end
    end
  end
endmodule

//ROM - Sí funciona
module ROM_Memory (input wire [11:0]address, output wire [7:0]opcode);
  reg [7:0] ROM [0:4095];
  initial begin
      $readmemh("codigo.list", ROM);
  end
  assign opcode = ROM[address];
endmodule

// Flip Flop Tipo D --> para fetch
module flip_flop8 (input wire clk, reset, enable, input wire [7:0]d, output reg [7:0]q);
	always @ (posedge clk or posedge reset or enable)begin
		if (reset) begin
			q <= 8'b0;
		end
    else if (enable) begin
      q <= d;
    end
	end
endmodule

//Fetch - Sí funciona
module Fetch (input wire clk, reset, enable, input wire [7:0]opcode, output wire [3:0]instruction, operand);
  wire [7:0]q;
  assign instruction = q[7:4];
  assign operand = q[3:0];
  flip_flop8 F1(clk, reset, enable, opcode, q);
endmodule

// Flip Flop Tipo D --> para flags - Sí funciona
module Flags (input wire clk, reset, enable, input wire [1:0]d, output reg [1:0]q);
	always @ (posedge clk or posedge reset or enable)begin
		if (reset) begin
			q <= 2'b0;
		end
    else if (enable) begin
      q <= d;
    end
	end
endmodule

// Flip Flop Tipo D --> para toggle del phase
module flip_flop1 (input wire clk, reset, enable, input wire d, output reg q);
	always @ (posedge clk or posedge reset or enable)begin
		if (reset) begin
			q <= 1'b0;
		end
    else if (enable) begin
      q <= d;
    end
	end
endmodule

// Flip Flop Toggle --> para phase - Sí funciona
module Phase (input wire clk, reset, enable, output wire q);
  wire d;
  assign d = ~q;
	flip_flop1 F1(clk, reset, enable, d, q);
endmodule

//Decode
module Microcode(input wire [6:0]address, output reg [12:0]control);
  always @ (address) begin
    casex (address)
    7'bxxxxxx0: //0
      control <= 13'b1000000001000;
    7'b00001x1: //1
      control <= 13'b0100000001000;
    7'b00000x1: //2
      control <= 13'b1000000001000;
    7'b00011x1: //3
      control <= 13'b1000000001000;
    7'b00010x1: //4
      control <= 13'b0100000001000;
    7'b0010xx1: //5
      control <= 13'b0001001000010;
    7'b0011xx1: //6
      control <= 13'b1001001100000;
    7'b0100xx1: //7
      control <= 13'b0011010000010;
    7'b0101xx1: //8
      control <= 13'b0011010000100;
    7'b0110xx1: //9
      control <= 13'b1011010100000;
    7'b0111xx1: //10
      control <= 13'b1000000111000;
    7'b1000x11: //11
      control <= 13'b0100000001000;
    7'b1000x01: //12
      control <= 13'b1000000001000;
    7'b1001x11: //13
      control <= 13'b1000000001000;
    7'b1001x01: //14
      control <= 13'b0100000001000;
    7'b1010xx1: //15
      control <= 13'b0011011000010;
    7'b1011xx1: //16
      control <= 13'b1011011100000;
    7'b1100xx1: //17
      control <= 13'b0100000001000;
    7'b1101xx1: //18
      control <= 13'b0000000001001;
    7'b1110xx1: //19
      control <= 13'b0011100000010;
    7'b1111xx1: //20
      control <= 13'b1011100100000;
    default:
      control <= 13'b1111111111111;
    endcase
  end
endmodule

// Buffer Tri-estado - Sí funciona
module Tris (input wire enable, input wire [3:0]in, output wire [3:0]out);
  assign out = enable ? in:4'bz;
endmodule

//RAM
module RAM_Memory (input wire enable, write, read, input wire [11:0]address_RAM, inout [3:0]data);
  reg [3:0] RAM [0:4095];
  reg [3:0]data_out;

  //Coloca un tris para poder escribir o leer
  assign data = (enable & read & ~write) ? data_out:4'bz;
  //Bloque de escritura
  always @ ( address_RAM or data or enable or write ) begin
    if (enable && write) begin
      RAM[address_RAM] = data;
    end
  end
  //Bloque de lectura
  always @ ( address_RAM or enable or write or read) begin
    if (enable && ~write && read) begin
      data_out = RAM[address_RAM];
    end
  end
endmodule

// Flip Flop Tipo D - Sí funciona
module Accumulator (input wire clk, reset, enable, input wire [3:0]result, output reg [3:0]accu);
	always @ (posedge clk or posedge reset or enable) begin
		if (reset) begin
			accu <= 4'b0;
		end
    else if (enable) begin
      accu <= result;
    end
	end
endmodule

//ALU - Los 3 bits de seleccion vienen del microcode el databus es el operand y la accu es W
module ALU (input wire [3:0]data_bus, accu, input wire [2:0]selector, output reg [3:0]result, output wire [1:0]flags);
  wire zero;
  reg carry;
  always @ ( * ) begin
    case (selector)
    0:
      {carry, result} <= accu;
    1:
      {carry, result} <= accu - data_bus;
    2:
      {carry, result} <= data_bus;
    3:
      {carry, result} <= accu + data_bus;
    4:
      {carry, result} <= accu ~& data_bus;
    default:
      {carry, result} <= 5'b0;
    endcase
  end
  assign zero = ((result == 4'b0) && (carry == 1'b0)) ? 1'b1:1'b0;
  assign flags[0] = zero;
  assign flags[1] = carry;
endmodule

// Flip Flop Tipo D --> para outputs
module Outputs (input wire clk, reset, enable, input wire [3:0]d, output reg [3:0]q);
	always @ (posedge clk or posedge reset or enable)begin
		if (reset) begin
			q <= 4'b0;
		end
    else if (enable) begin
      q <= d;
    end
	end
endmodule

//Nibbler
module uP (input wire clock, reset, input wire [3:0]pushbuttons, output wire phase, c_flag, z_flag, output wire [3:0]instr, oprnd, data_bus, FF_out, accu, output wire [7:0]program_byte, output wire [11:0]pc, address_ram);
  //Cables internos del Nibbler
  wire oeRAM;
  wire [1:0]flags_in, flags_out; //posicion 1 es carry y 0 es zero
  wire [12:0]control;
  wire [3:0]alu_result;
  wire [6:0]address;
  //Defino a address como la contatenacion de varias entradas
  assign address = {instr, c_flag, z_flag, phase};
  //address_RAM
  //assign address_ram[11:8] = oprnd;
  //assign address_ram[7:0] = program_byte;
  //Defino mis banderas concatenadas
  assign c_flag = flags_out[1];
  assign z_flag = flags_out[0];
  //oeRAM definición - Se activa cuando los buffers triestado estan apagados
  assign oeRAM = ~control[1] & ~control[2] & ~control[3];
  //Defino a los bits de control con mi address a traves del decode
  Microcode M1(address, control);
  //Doy valor al PC a traves de las señales de control 11 y 12 -load y enable respectivamente-
  Counter PC1(clock, reset, control[11], control[12], address_ram, pc);
  //Busco la instruccion correspondiente en la ROM con el PC
  ROM_Memory ROM1(pc, program_byte);
  //Fetch divide al program_byte -opcode- en instruccion y operando
  Fetch FE1(clock, reset, ~phase, program_byte, instr, oprnd);
  //Uso el toggle para definir el phase
  Phase PH1(clock, reset, 1'b1, phase); //Enable del phase siempre en 1?????
  //Dejo pasar mis banderas con el bit 9 de control -LoadFlags-
  Flags FL1(clock, reset, control[9], flags_in, flags_out);
  //Primer Bus Driver - Defino a data_bus usando el bit 1 de control -oeOprnd-
  Tris BD1(control[1], oprnd, data_bus);
  //Operaciones con ALU entra data_bus y accu, selecciono con los bits 6, 7 y 8 de control, sale el resultado y las banderas
  ALU A1(data_bus, accu, control[8:6], alu_result, flags_in);
  //Genero el registro W - Defino a accu a traves del resultado de la ALU y del bit 10 de control -loadA-
  Accumulator A2(clock, reset, control[10], alu_result, accu);
  //Segundo Bus Driver - Defino a data_bus usando el bit 3 de control -oeALU-
  Tris BD2(control[3], alu_result, data_bus);
  //Definicion de la RAM uso de control 4 y 5 -weRAM y csRAM respectivamente-
  RAM_Memory RAM1(control[5], control[4], oeRAM, address_ram, data_bus); //output enable de la RAM es cuando los otros tres tris estan en cero????
  //Tercer Bus Driver - Defino a data_bus usando el bit 2 de control -oeIN-
  Tris BD3(control[2], pushbuttons, data_bus);
  //Flip flop para Outputs con bit 0 de control -loadOut-
  Outputs O1(clock, reset, control[0], data_bus, FF_out);
endmodule

Nibbler/uP_tb.v
module testbench();
  //Variables de entrada
  reg clock, reset;
  reg [3:0]pushbuttons;

  //Variables de salida
  wire phase, c_flag, z_flag;
  wire [3:0]instr, oprnd, data_bus, FF_out, accu;
  wire [7:0]program_byte;
  wire [11:0]pc, address_ram;
  //Instanciaciones
  uP MicroProcessor(clock, reset, pushbuttons, phase, c_flag, z_flag, instr, oprnd, data_bus, FF_out, accu, program_byte, pc, address_ram);

  always
    #5 clock <=~clock;

    //Ejercicio 1
    initial begin
    #2
    $display(" \nNibbler ");
    $display("clock reset pushbuttons |  phase  c_flag   z_flag   instr   oprnd   data_bus  FF_out   Accu   program_byte       PC          address_ram ");
    $display("------------------------|----------------------------------------------------------------------------------------------------------------");
    $monitor("%b       %b       %b    |   %b       %b        %b      %b    %b     %b      %b    %b     %b     %b    %b ", clock, reset, pushbuttons, phase, c_flag, z_flag, instr, oprnd, data_bus, FF_out, accu, program_byte, pc, address_ram);

      reset = 1; clock = 0; pushbuttons = 4'b0;
  #1  reset = 0; pushbuttons = 4'b1010;
    end

    initial
      #210 $finish;
    initial begin
        $dumpfile("uP_tb.vcd");
        $dumpvars(0, testbench);
      end
  endmodule

Nibbler/uP_tb.vcd
$date
	Sat Nov 14 20:38:53 2020
$end
$version
	Icarus Verilog
$end
$timescale
	1ps
$end
$scope module testbench $end
$var wire 12 ! address_ram [11:0] $end
$var wire 4 " data_bus [3:0] $end
$var wire 1 # z_flag $end
$var wire 8 $ program_byte [7:0] $end
$var wire 1 % phase $end
$var wire 12 & pc [11:0] $end
$var wire 4 ' oprnd [3:0] $end
$var wire 4 ( instr [3:0] $end
$var wire 1 ) c_flag $end
$var wire 4 * accu [3:0] $end
$var wire 4 + FF_out [3:0] $end
$var reg 1 , clock $end
$var reg 4 - pushbuttons [3:0] $end
$var reg 1 . reset $end
$scope module MicroProcessor $end
$var wire 12 / address_ram [11:0] $end
$var wire 1 , clock $end
$var wire 4 0 data_bus [3:0] $end
$var wire 1 1 oeRAM $end
$var wire 4 2 pushbuttons [3:0] $end
$var wire 1 . reset $end
$var wire 1 # z_flag $end
$var wire 8 3 program_byte [7:0] $end
$var wire 1 % phase $end
$var wire 12 4 pc [11:0] $end
$var wire 4 5 oprnd [3:0] $end
$var wire 4 6 instr [3:0] $end
$var wire 2 7 flags_out [1:0] $end
$var wire 2 8 flags_in [1:0] $end
$var wire 13 9 control [12:0] $end
$var wire 1 ) c_flag $end
$var wire 4 : alu_result [3:0] $end
$var wire 7 ; address [6:0] $end
$var wire 4 < accu [3:0] $end
$var wire 4 = FF_out [3:0] $end
$scope module A1 $end
$var wire 4 > data_bus [3:0] $end
$var wire 3 ? selector [2:0] $end
$var wire 1 @ zero $end
$var wire 2 A flags [1:0] $end
$var wire 4 B accu [3:0] $end
$var reg 1 C carry $end
$var reg 4 D result [3:0] $end
$upscope $end
$scope module A2 $end
$var wire 1 , clk $end
$var wire 1 E enable $end
$var wire 1 . reset $end
$var wire 4 F result [3:0] $end
$var reg 4 G accu [3:0] $end
$upscope $end
$scope module BD1 $end
$var wire 1 H enable $end
$var wire 4 I out [3:0] $end
$var wire 4 J in [3:0] $end
$upscope $end
$scope module BD2 $end
$var wire 1 K enable $end
$var wire 4 L in [3:0] $end
$var wire 4 M out [3:0] $end
$upscope $end
$scope module BD3 $end
$var wire 1 N enable $end
$var wire 4 O in [3:0] $end
$var wire 4 P out [3:0] $end
$upscope $end
$scope module FE1 $end
$var wire 1 , clk $end
$var wire 1 Q enable $end
$var wire 1 . reset $end
$var wire 8 R q [7:0] $end
$var wire 4 S operand [3:0] $end
$var wire 8 T opcode [7:0] $end
$var wire 4 U instruction [3:0] $end
$scope module F1 $end
$var wire 1 , clk $end
$var wire 1 Q enable $end
$var wire 1 . reset $end
$var wire 8 V d [7:0] $end
$var reg 8 W q [7:0] $end
$upscope $end
$upscope $end
$scope module FL1 $end
$var wire 1 , clk $end
$var wire 2 X d [1:0] $end
$var wire 1 Y enable $end
$var wire 1 . reset $end
$var reg 2 Z q [1:0] $end
$upscope $end
$scope module M1 $end
$var wire 7 [ address [6:0] $end
$var reg 13 \ control [12:0] $end
$upscope $end
$scope module O1 $end
$var wire 1 , clk $end
$var wire 4 ] d [3:0] $end
$var wire 1 ^ enable $end
$var wire 1 . reset $end
$var reg 4 _ q [3:0] $end
$upscope $end
$scope module PC1 $end
$var wire 1 , clock $end
$var wire 1 ` enable $end
$var wire 1 a load $end
$var wire 12 b load_data [11:0] $end
$var wire 1 . reset $end
$var reg 12 c value [11:0] $end
$upscope $end
$scope module PH1 $end
$var wire 1 , clk $end
$var wire 1 d d $end
$var wire 1 e enable $end
$var wire 1 . reset $end
$var wire 1 % q $end
$scope module F1 $end
$var wire 1 , clk $end
$var wire 1 d d $end
$var wire 1 e enable $end
$var wire 1 . reset $end
$var reg 1 % q $end
$upscope $end
$upscope $end
$scope module RAM1 $end
$var wire 12 f address_RAM [11:0] $end
$var wire 4 g data [3:0] $end
$var wire 1 h enable $end
$var wire 1 1 read $end
$var wire 1 i write $end
$var reg 4 j data_out [3:0] $end
$upscope $end
$scope module ROM1 $end
$var wire 12 k address [11:0] $end
$var wire 8 l opcode [7:0] $end
$upscope $end
$upscope $end
$upscope $end
$enddefinitions $end
#0
$dumpvars
bx l
bx k
bx j
xi
xh
bx g
bz f
1e
xd
bx c
bz b
xa
x`
bx _
x^
bx ]
bx \
bx [
bx Z
xY
bx X
bx W
bx V
bx U
bx T
bx S
bx R
xQ
bx P
bx O
xN
bx M
bx L
xK
bx J
bx I
xH
bx G
bx F
xE
bx D
xC
bx B
bx A
x@
bx ?
bx >
bx =
bx <
bx ;
bx :
bx 9
bx 8
bx 7
bx 6
bx 5
bx 4
bx 3
bx 2
x1
bx 0
bz /
x.
bx -
x,
bx +
bx *
x)
bx (
bx '
bx &
x%
bx $
x#
bx "
bz !
$end
#2
b0 "
b0 0
b0 >
b0 I
b0 M
b0 P
b0 ]
b0 g
1@
01
0^
0N
0i
0h
1K
0E
b0 ?
0H
0Y
1`
0a
b1 8
b1 A
b1 X
0C
b0 :
b0 D
b0 F
b0 L
b1000000001000 9
b1000000001000 \
b0 '
b0 5
b0 J
b0 S
b0 (
b0 6
b0 U
0#
0)
1d
1Q
b0 *
b0 <
b0 B
b0 G
b0 R
b0 W
b0 7
b0 Z
b0 +
b0 =
b0 _
b1001110 $
b1001110 3
b1001110 T
b1001110 V
b1001110 l
b0 &
b0 4
b0 c
b0 k
b0 ;
b0 [
0%
b0 -
b0 2
b0 O
0,
1.
#3
b1010 -
b1010 2
b1010 O
0.
#5
b0 8
b0 A
b0 X
0@
1#
b1110 :
b1110 D
b1110 F
b1110 L
b1 7
b1 Z
b1110 "
b1110 0
b1110 >
b1110 I
b1110 M
b1110 P
b1110 ]
b1110 g
0K
1E
b10 ?
1H
1Y
0`
b11010000010 9
b11010000010 \
b1110 '
b1110 5
b1110 J
b1110 S
b100 (
b100 6
b100 U
0d
0Q
b1001110 R
b1001110 W
b101111 $
b101111 3
b101111 T
b101111 V
b101111 l
b1 &
b1 4
b1 c
b1 k
b100011 ;
b100011 [
1%
1,
#10
0,
#15
b1110 "
b1110 0
b1110 >
b1110 I
b1110 M
b1110 P
b1110 ]
b1110 g
b1111 '
b1111 5
b1111 J
b1111 S
b10 (
b10 6
b10 U
1K
0E
b0 ?
0H
0Y
1`
b101111 R
b101111 W
b1000000001000 9
b1000000001000 \
0#
1d
1Q
b1110 *
b1110 <
b1110 B
b1110 G
b0 7
b0 Z
b10000 ;
b10000 [
0%
1,
#20
0,
#25
b10 8
b10 A
b10 X
1C
b1111 :
b1111 D
b1111 F
b1111 L
b1111 "
b1111 0
b1111 >
b1111 I
b1111 M
b1111 P
b1111 ]
b1111 g
0K
b1 ?
1H
1Y
0`
b1001000010 9
b1001000010 \
0d
0Q
b11010100 $
b11010100 3
b11010100 T
b11010100 V
b11010100 l
b10 &
b10 4
b10 c
b10 k
b10001 ;
b10001 [
1%
1,
#30
0,
#35
b0 8
b0 A
b0 X
0C
b1110 :
b1110 D
b1110 F
b1110 L
b1110 "
b1110 0
b1110 >
b1110 I
b1110 M
b1110 P
b1110 ]
b1110 g
b100 '
b100 5
b100 J
b100 S
b1101 (
b1101 6
b1101 U
1K
b0 ?
0H
0Y
1`
b11010100 R
b11010100 W
b1000000001000 9
b1000000001000 \
1)
1d
1Q
b10 7
b10 Z
b1101100 ;
b1101100 [
0%
1,
#40
0,
#45
b1110 +
b1110 =
b1110 _
1^
0`
b1001 9
b1001 \
0d
0Q
b10100101 $
b10100101 3
b10100101 T
b10100101 V
b10100101 l
b11 &
b11 4
b11 c
b11 k
b1101101 ;
b1101101 [
1%
1,
#50
0,
#55
b101 '
b101 5
b101 J
b101 S
b1010 (
b1010 6
b1010 U
0^
1`
b10100101 R
b10100101 W
b1000000001000 9
b1000000001000 \
1d
1Q
b1010100 ;
b1010100 [
0%
1,
#60
0,
#65
0)
b10 8
b10 A
b10 X
1C
b11 :
b11 D
b11 F
b11 L
b0 7
b0 Z
b101 "
b101 0
b101 >
b101 I
b101 M
b101 P
b101 ]
b101 g
0K
1E
b11 ?
1H
1Y
0`
b11011000010 9
b11011000010 \
0d
0Q
b1010111 $
b1010111 3
b1010111 T
b1010111 V
b1010111 l
b100 &
b100 4
b100 c
b100 k
b1010001 ;
b1010001 [
1%
1,
#70
0,
#75
b11 "
b11 0
b11 >
b11 I
b11 M
b11 P
b11 ]
b11 g
b111 '
b111 5
b111 J
b111 S
b101 (
b101 6
b101 U
1K
0E
b0 ?
0H
0Y
1`
b1010111 R
b1010111 W
b0 8
b0 A
b0 X
0C
b11 :
b11 D
b11 F
b11 L
b1000000001000 9
b1000000001000 \
1)
1d
1Q
b11 *
b11 <
b11 B
b11 G
b10 7
b10 Z
b101100 ;
b101100 [
0%
1,
#80
0,
#85
0)
b1010 :
b1010 D
b1010 F
b1010 L
b0 7
b0 Z
b1010 "
b1010 0
b1010 >
b1010 I
b1010 M
b1010 P
b1010 ]
b1010 g
1N
0K
1E
b10 ?
1Y
0`
b11010000100 9
b11010000100 \
0d
0Q
b11101010 $
b11101010 3
b11101010 T
b11101010 V
b11101010 l
b101 &
b101 4
b101 c
b101 k
b101001 ;
b101001 [
1%
1,
#90
0,
#95
b1010 '
b1010 5
b1010 J
b1010 S
b1110 (
b1110 6
b1110 U
0N
1K
0E
b0 ?
0Y
1`
b11101010 R
b11101010 W
b1000000001000 9
b1000000001000 \
1d
1Q
b1010 *
b1010 <
b1010 B
b1010 G
b1110000 ;
b1110000 [
0%
1,
#100
0,
#105
b10 8
b10 A
b10 X
1C
b101 :
b101 D
b101 F
b101 L
0K
1E
b100 ?
1H
1Y
0`
b11100000010 9
b11100000010 \
0d
0Q
b11000000 $
b11000000 3
b11000000 T
b11000000 V
b11000000 l
b110 &
b110 4
b110 c
b110 k
b1110001 ;
b1110001 [
1%
1,
#110
0,
#115
b0 8
b0 A
b0 X
0C
b101 "
b101 0
b101 >
b101 I
b101 M
b101 P
b101 ]
b101 g
b0 '
b0 5
b0 J
b0 S
b1100 (
b1100 6
b1100 U
1K
0E
b0 ?
0H
0Y
1`
b11000000 R
b11000000 W
b101 :
b101 D
b101 F
b101 L
b1000000001000 9
b1000000001000 \
1)
1d
1Q
b101 *
b101 <
b101 B
b101 G
b10 7
b10 Z
b1100100 ;
b1100100 [
0%
1,
#120
0,
#125
0`
1a
b100000001000 9
b100000001000 \
0d
0Q
bx $
bx 3
bx T
bx V
bx l
bz &
bz 4
bz c
bz k
b1100101 ;
b1100101 [
1%
1,
#130
0,
#135
bx '
bx 5
bx J
bx S
bx (
bx 6
bx U
1`
0a
bx R
bx W
b1000000001000 9
b1000000001000 \
1d
1Q
bx100 ;
bx100 [
0%
1,
#140
0,
#145
0`
1a
b100000001000 9
b100000001000 \
0d
0Q
bx101 ;
bx101 [
1%
1,
#150
0,
#155
1`
0a
b1000000001000 9
b1000000001000 \
1d
1Q
bx100 ;
bx100 [
0%
1,
#160
0,
#165
0`
1a
b100000001000 9
b100000001000 \
0d
0Q
bx101 ;
bx101 [
1%
1,
#170
0,
#175
1`
0a
b1000000001000 9
b1000000001000 \
1d
1Q
bx100 ;
bx100 [
0%
1,
#180
0,
#185
0`
1a
b100000001000 9
b100000001000 \
0d
0Q
bx101 ;
bx101 [
1%
1,
#190
0,
#195
1`
0a
b1000000001000 9
b1000000001000 \
1d
1Q
bx100 ;
bx100 [
0%
1,
#200
0,
#205
0`
1a
b100000001000 9
b100000001000 \
0d
0Q
bx101 ;
bx101 [
1%
1,
