Nibbler/uP.v
//-----------------------------------
// Ricardo Pellecer Orellana
// Carné: 19072
// 22/Noviembre/2020
// -----------------------------------

//Program Counter - Sí funciona
module Counter (input wire clock, reset, load, enable, input wire [11:0]load_data, output reg [11:0]value);
  always @ (posedge clock, posedge reset, load, load_data) begin
    if (reset) begin
      value <= 12'b0;
    end
    else if (load) begin
      value <= load_data;
    end
    else if (enable) begin
      if (value < 12'b111111111111) begin
        value <= value + 1;
      end
    end
  end
endmodule

//ROM - Sí funciona
module ROM_Memory (input wire [11:0]address, output wire [7:0]opcode);
  reg [7:0] ROM [0:4095];
  initial begin
      $readmemh("codigo.list", ROM);
  end
  assign opcode = ROM[address];
endmodule

// Flip Flop Tipo D --> para fetch
module flip_flop8 (input wire clk, reset, enable, input wire [7:0]d, output reg [7:0]q);
	always @ (posedge clk or posedge reset or enable)begin
		if (reset) begin
			q <= 8'b0;
		end
    else if (enable) begin
      q <= d;
    end
	end
endmodule

//Fetch
module Fetch (input wire clk, reset, enable, input wire [7:0]opcode, output wire [3:0]instruction, operand);
  wire [7:0]q;
  assign instruction = q[7:4];
  assign operand = q[3:0];
  flip_flop8 F1(clk, reset, enable, opcode, q);
endmodule

// Flip Flop Tipo D --> para flags
module Flags (input wire clk, reset, enable, input wire [1:0]d, output reg [1:0]q);
	always @ (posedge clk or posedge reset or enable)begin
		if (reset) begin
			q <= 2'b0;
		end
    else if (enable) begin
      q <= d;
    end
	end
endmodule

// Flip Flop Tipo D --> para toggle del phase
module flip_flop1 (input wire clk, reset, enable, input wire d, output reg q);
	always @ (posedge clk or posedge reset or enable)begin
		if (reset) begin
			q <= 1'b0;
		end
    else if (enable) begin
      q <= d;
    end
	end
endmodule

// Flip Flop Toggle --> para phase
module Phase (input wire clk, reset, enable, output wire q);
  wire d;
  assign d = ~q;
	flip_flop1 F1(clk, reset, enable, d, q);
endmodule

//Decode
module Microcode(input wire [6:0]address, output reg [12:0]control);
  always @ ( * ) begin
    casex (address)
    7'bxxxxxx0: //0
      control <= 13'b1000000001000;
    7'b00001x1: //1
      control <= 13'b0100000001000;
    7'b00000x1: //2
      control <= 13'b1000000001000;
    7'b00011x1: //3
      control <= 13'b1000000001000;
    7'b00010x1: //4
      control <= 13'b0100000001000;
    7'b0010xx1: //5
      control <= 13'b0001001000010;
    7'b0011xx1: //6
      control <= 13'b1001001100000;
    7'b0100xx1: //7
      control <= 13'b0011010000010;
    7'b0101xx1: //8
      control <= 13'b0011010000100;
    7'b0110xx1: //9
      control <= 13'b1011010100000;
    7'b0111xx1: //10
      control <= 13'b1000000111000;
    7'b1000x11: //11
      control <= 13'b0100000001000;
    7'b1000x01: //12
      control <= 13'b1000000001000;
    7'b1001x11: //13
      control <= 13'b1000000001000;
    7'b1001x01: //14
      control <= 13'b0100000001000;
    7'b1010xx1: //15
      control <= 13'b0011011000010;
    7'b1011xx1: //16
      control <= 13'b1011011100000;
    7'b1100xx1: //17
      control <= 13'b0100000001000;
    7'b1101xx1: //18
      control <= 13'b0000000001001;
    7'b1110xx1: //19
      control <= 13'b0011100000010;
    7'b1111xx1: //20
      control <= 13'b1011100100000;
    default:
      control <= 13'b0;
    endcase
  end
endmodule

// Buffer Tri-estado --> Funciona
module Tris (input wire enable, input wire [3:0]in, output wire [3:0]out);
  assign out = enable ? in:4'bz;
endmodule

//RAM
module RAM_Memory (input wire enable, write, read, input wire [11:0]address_RAM, inout [3:0]data);
  reg [3:0] RAM [0:4095];
  reg [3:0]data_out;

  //Coloca un tris para poder escribir o leer
  assign data = (enable & read & ~write) ? data_out:4'bz;
  //Bloque de escritura
  always @ ( address_RAM or data or enable or write ) begin
    if (enable && write) begin
      RAM[address_RAM] = data;
    end
  end
  //Bloque de lectura
  always @ ( address_RAM or enable or write or read) begin
    if (enable && ~write && read) begin
      data_out = RAM[address_RAM];
    end
  end
endmodule

// Flip Flop Tipo D
module Accumulator (input wire clk, reset, enable, input wire [3:0]result, output reg [3:0]accu);
	always @ (posedge clk or posedge reset or enable) begin
		if (reset) begin
			accu <= 4'b0;
		end
    else if (enable) begin
      accu <= result;
    end
	end
endmodule

//ALU - Los 3 bits de seleccion vienen del microcode el databus es el operand y la accu es W
module ALU (input wire [3:0]data_bus, accu, input wire [2:0]selector, output wire [3:0]result, output wire [1:0]flags);
  wire zero, carry;
  reg [4:0]result_flags;
  always @ ( * ) begin
    case (selector)
    0:
      result_flags <= accu;
    1:
      result_flags <= accu - data_bus;
    2:
      result_flags <= data_bus;
    3:
      result_flags <= accu + data_bus;
    4:
      result_flags <= accu ~& data_bus;
    default:
      result_flags <= 5'b0;
    endcase
  end
  assign result = result_flags[3:0];
  assign carry = result_flags[4];
  assign zero = (result_flags == 5'b0) ? 1'b1:1'b0;
  assign flags[0] = zero;
  assign flags[1] = carry;
endmodule

// Flip Flop Tipo D --> para outputs
module Outputs (input wire clk, reset, enable, input wire [3:0]d, output reg [3:0]q);
	always @ (posedge clk or posedge reset or enable)begin
		if (reset) begin
			q <= 4'b0;
		end
    else if (enable) begin
      q <= d;
    end
	end
endmodule

//Nibbler
module uP (input wire clock, reset, input wire [3:0]pushbuttons, output wire phase, c_flag, z_flag, output wire [3:0]instr, oprnd, data_bus, FF_out, accu, output wire [7:0]program_byte, output wire [11:0]pc, address_ram);
  //Cables internos del Nibbler
  wire oeRAM;
  wire [1:0]flags_in, flags_out; //posicion 1 es carry y 0 es zero
  wire [12:0]control;
  wire [3:0]alu_result;
  wire [6:0]address;
  //Defino a address como la contatenacion de varias entradas
  assign address[6:3] = instr;
  assign address[2] = c_flag;
  assign address[1] = z_flag;
  assign address[0] = phase;
  //Defino mis banderas concatenadas
  assign c_flag = flags_out[1];
  assign z_flag = flags_out[0];
  //oeRAM definición - Se activa cuando los buffers triestado estan apagados
  assign oeRAM = ~control[1] & ~control[2] & ~control[3];
  //Defino a los bits de control con mi address a traves del decode
  Microcode M1(address, control);
  //Doy valor al PC a traves de las señales de control 11 y 12 -load y enable respectivamente-
  Counter PC1(clock, reset, control[11], control[12], address_ram, pc);
  //Busco la instruccion correspondiente en la ROM con el PC
  ROM_Memory ROM1(pc, program_byte);
  //Fetch divide al program_byte -opcode- en instruccion y operando
  Fetch FE1(clock, reset, ~phase, program_byte, instr, oprnd);
  //Uso el toggle para definir el phase
  Phase PH1(clock, reset, 1'b1, phase); //Enable del phase siempre en 1?????
  //Dejo pasar mis banderas con el bit 9 de control -LoadFlags-
  Flags FL1(clock, reset, control[9], flags_in, flags_out);
  //Primer Bus Driver - Defino a data_bus usando el bit 1 de control -oeOprnd-
  Tris BD1(control[1], oprnd, data_bus);
  //Operaciones con ALU entra data_bus y accu, selecciono con los bits 6, 7 y 8 de control, sale el resultado y las banderas
  ALU A1(data_bus, accu, control[8:6], alu_result, flags_in);
  //Genero el registro W - Defino a accu a traves del resultado de la ALU y del bit 10 de control -loadA-
  Accumulator A2(clock, reset, control[10], alu_result, accu);
  //Segundo Bus Driver - Defino a data_bus usando el bit 3 de control -oeALU-
  Tris BD2(control[3], alu_result, data_bus);
  //Definicion de la RAM uso de control 4 y 5 -weRAM y csRAM respectivamente-
  RAM_Memory RAM1(control[5], control[4], oeRAM, address_ram, data_bus); //output enable de la RAM es cuando los otros tres tris estan en cero????
  //Tercer Bus Driver - Defino a data_bus usando el bit 2 de control -oeIN-
  Tris BD3(control[2], pushbuttons, data_bus);
  //Flip flop para Outputs con bit 0 de control -loadOut-
  Outputs O1(clock, reset, control[0], data_bus, FF_out);
endmodule

Nibbler/uP_tb.v
module testbench();
  //Variables de entrada
  reg clock, reset;
  reg [3:0]pushbuttons;

  //Variables de salida
  wire phase, c_flag, z_flag;
  wire [3:0]instr, oprnd, data_bus, FF_out, accu;
  wire [7:0]program_byte;
  wire [11:0]pc, address_ram;
  //Instanciaciones
  uP MicroProcessor(clock, reset, pushbuttons, phase, c_flag, z_flag, instr, oprnd, data_bus, FF_out, accu, program_byte, pc, address_ram);

  always
    #5 clock <=~clock;

    //Ejercicio 1
    initial begin
    #2
    $display(" \nNibbler ");
    $display("clock reset pushbuttons |  phase  c_flag   z_flag   instr   oprnd   data_bus  FF_out   Accu   program_byte       PC          address_ram ");
    $display("------------------------|----------------------------------------------------------------------------------------------------------------");
    $monitor("%b       %b       %b    |   %b       %b        %b      %b    %b     %b      %b    %b     %b     %b    %b", clock, reset, pushbuttons, phase, c_flag, z_flag, instr, oprnd, data_bus, FF_out, accu, program_byte, pc, address_ram);

      reset = 1; clock = 0; pushbuttons = 4'b0;
  #2  reset = 0; pushbuttons = 4'b0;
    end

    initial
      #60 $finish;
    initial begin
        $dumpfile("uP_tb.vcd");
        $dumpvars(0, testbench);
      end
  endmodule

Nibbler/uP_tb.vcd
$date
	Sat Nov 14 15:42:00 2020
$end
$version
	Icarus Verilog
$end
$timescale
	1ps
$end
$scope module testbench $end
$var wire 12 ! address_ram [11:0] $end
$var wire 4 " data_bus [3:0] $end
$var wire 1 # z_flag $end
$var wire 8 $ program_byte [7:0] $end
$var wire 1 % phase $end
$var wire 12 & pc [11:0] $end
$var wire 4 ' oprnd [3:0] $end
$var wire 4 ( instr [3:0] $end
$var wire 1 ) c_flag $end
$var wire 4 * accu [3:0] $end
$var wire 4 + FF_out [3:0] $end
$var reg 1 , clock $end
$var reg 4 - pushbuttons [3:0] $end
$var reg 1 . reset $end
$scope module MicroProcessor $end
$var wire 12 / address_ram [11:0] $end
$var wire 1 , clock $end
$var wire 4 0 data_bus [3:0] $end
$var wire 1 1 oeRAM $end
$var wire 4 2 pushbuttons [3:0] $end
$var wire 1 . reset $end
$var wire 1 # z_flag $end
$var wire 8 3 program_byte [7:0] $end
$var wire 1 % phase $end
$var wire 12 4 pc [11:0] $end
$var wire 4 5 oprnd [3:0] $end
$var wire 4 6 instr [3:0] $end
$var wire 2 7 flags_out [1:0] $end
$var wire 2 8 flags_in [1:0] $end
$var wire 13 9 control [12:0] $end
$var wire 1 ) c_flag $end
$var wire 4 : alu_result [3:0] $end
$var wire 7 ; address [6:0] $end
$var wire 4 < accu [3:0] $end
$var wire 4 = FF_out [3:0] $end
$scope module A1 $end
$var wire 4 > data_bus [3:0] $end
$var wire 3 ? selector [2:0] $end
$var wire 1 @ zero $end
$var wire 4 A result [3:0] $end
$var wire 2 B flags [1:0] $end
$var wire 1 C carry $end
$var wire 4 D accu [3:0] $end
$var reg 5 E result_flags [4:0] $end
$upscope $end
$scope module A2 $end
$var wire 1 , clk $end
$var wire 1 F enable $end
$var wire 1 . reset $end
$var wire 4 G result [3:0] $end
$var reg 4 H accu [3:0] $end
$upscope $end
$scope module BD1 $end
$var wire 1 I enable $end
$var wire 4 J out [3:0] $end
$var wire 4 K in [3:0] $end
$upscope $end
$scope module BD2 $end
$var wire 1 L enable $end
$var wire 4 M in [3:0] $end
$var wire 4 N out [3:0] $end
$upscope $end
$scope module BD3 $end
$var wire 1 O enable $end
$var wire 4 P in [3:0] $end
$var wire 4 Q out [3:0] $end
$upscope $end
$scope module FE1 $end
$var wire 1 , clk $end
$var wire 1 R enable $end
$var wire 1 . reset $end
$var wire 8 S q [7:0] $end
$var wire 4 T operand [3:0] $end
$var wire 8 U opcode [7:0] $end
$var wire 4 V instruction [3:0] $end
$scope module F1 $end
$var wire 1 , clk $end
$var wire 1 R enable $end
$var wire 1 . reset $end
$var wire 8 W d [7:0] $end
$var reg 8 X q [7:0] $end
$upscope $end
$upscope $end
$scope module FL1 $end
$var wire 1 , clk $end
$var wire 2 Y d [1:0] $end
$var wire 1 Z enable $end
$var wire 1 . reset $end
$var reg 2 [ q [1:0] $end
$upscope $end
$scope module M1 $end
$var wire 7 \ address [6:0] $end
$var reg 13 ] control [12:0] $end
$upscope $end
$scope module O1 $end
$var wire 1 , clk $end
$var wire 4 ^ d [3:0] $end
$var wire 1 _ enable $end
$var wire 1 . reset $end
$var reg 4 ` q [3:0] $end
$upscope $end
$scope module PC1 $end
$var wire 1 , clock $end
$var wire 1 a enable $end
$var wire 1 b load $end
$var wire 12 c load_data [11:0] $end
$var wire 1 . reset $end
$var reg 12 d value [11:0] $end
$upscope $end
$scope module PH1 $end
$var wire 1 , clk $end
$var wire 1 e d $end
$var wire 1 f enable $end
$var wire 1 . reset $end
$var wire 1 % q $end
$scope module F1 $end
$var wire 1 , clk $end
$var wire 1 e d $end
$var wire 1 f enable $end
$var wire 1 . reset $end
$var reg 1 % q $end
$upscope $end
$upscope $end
$scope module RAM1 $end
$var wire 12 g address_RAM [11:0] $end
$var wire 4 h data [3:0] $end
$var wire 1 i enable $end
$var wire 1 1 read $end
$var wire 1 j write $end
$var reg 4 k data_out [3:0] $end
$upscope $end
$scope module ROM1 $end
$var wire 12 l address [11:0] $end
$var wire 8 m opcode [7:0] $end
$upscope $end
$upscope $end
$upscope $end
$enddefinitions $end
#0
$dumpvars
bx m
bx l
bx k
xj
xi
bx h
bz g
1f
xe
bx d
bz c
xb
xa
bx `
x_
bx ^
bx ]
bx \
bx [
xZ
bx Y
bx X
bx W
bx V
bx U
bx T
bx S
xR
bx Q
bx P
xO
bx N
bx M
xL
bx K
bx J
xI
bx H
bx G
xF
bx E
bx D
xC
bx B
bx A
x@
bx ?
bx >
bx =
bx <
bx ;
bx :
bx 9
bx 8
bx 7
bx 6
bx 5
bx 4
bx 3
bx 2
x1
bx 0
bz /
x.
bx -
x,
bx +
bx *
x)
bx (
bx '
bx &
x%
bx $
x#
bx "
bz !
$end
#2
b0 "
b0 0
b0 >
b0 J
b0 N
b0 Q
b0 ^
b0 h
01
b0 :
b0 A
b0 G
b0 M
0C
b1 8
b1 B
b1 Y
1@
0_
0O
0j
0i
1L
0F
b0 ?
0I
0Z
1a
0b
b0 E
b1000000001000 9
b1000000001000 ]
b0 '
b0 5
b0 K
b0 T
b0 (
b0 6
b0 V
0#
0)
1e
1R
b0 *
b0 <
b0 D
b0 H
b0 S
b0 X
b0 7
b0 [
b0 +
b0 =
b0 `
b1001111 $
b1001111 3
b1001111 U
b1001111 W
b1001111 m
b0 &
b0 4
b0 d
b0 l
b0 ;
b0 \
0%
b0 -
b0 2
b0 P
0,
1.
#4
0.
#5
b1111 :
b1111 A
b1111 G
b1111 M
b0 8
b0 B
b0 Y
0@
1#
b1111 E
b1 7
b1 [
b1111 "
b1111 0
b1111 >
b1111 J
b1111 N
b1111 Q
b1111 ^
b1111 h
0L
1F
b10 ?
1I
1Z
0a
b11010000010 9
b11010000010 ]
b1111 '
b1111 5
b1111 K
b1111 T
b100 (
b100 6
b100 V
0e
0R
b1001111 S
b1001111 X
bx $
bx 3
bx U
bx W
bx m
b1 &
b1 4
b1 d
b1 l
b100011 ;
b100011 \
1%
1,
#10
0,
#15
b1111 "
b1111 0
b1111 >
b1111 J
b1111 N
b1111 Q
b1111 ^
b1111 h
bx '
bx 5
bx K
bx T
bx (
bx 6
bx V
1L
0F
b0 ?
0I
0Z
1a
bx S
bx X
b1000000001000 9
b1000000001000 ]
0#
1e
1R
b1111 *
b1111 <
b1111 D
b1111 H
b0 7
b0 [
bx000 ;
bx000 \
0%
1,
#20
0,
#25
0e
0R
b10 &
b10 4
b10 d
b10 l
bx001 ;
bx001 \
1%
1,
#30
0,
#35
1e
1R
b11 &
b11 4
b11 d
b11 l
bx000 ;
bx000 \
0%
1,
#40
0,
#45
0e
0R
b100 &
b100 4
b100 d
b100 l
bx001 ;
bx001 \
1%
1,
#50
0,
#55
1e
1R
b101 &
b101 4
b101 d
b101 l
bx000 ;
bx000 \
0%
1,
