codigo.v
//-----------------------------------
// Ricardo Pellecer Orellana
// Carné: 19072
// 9/Agosto/2020
// Gate Level Modelling 
// Tablas del Ejercicio 01: Tabla 01 y Tabla 02 
// Tablas del Ejercicio 02: Tabla 02 y Tabla 04
// Operadores
// Tablas del Ejercicio 01: Tabla 03 y Tabla 04
// Tablas del Ejercicio 02: Tabla 01 y Tabla 03
// -----------------------------------

// Ejercicio 1 Tabla 1;

module gateLevel_1(input wire A, B, C, output wire Y);

  wire notA, notB, notC, or1, or2;

  // Not's 
  
  not (notA, A);
  not (notB, B);
  not (notC, C);
  
  // Or's
  
  or  (or1, A, notC);
  or  (or2, notA, notB, C);
  
  // And's
  
  and (Y, or1, or2);
  
endmodule

// Ejercicio 1 Tabla 2;

module gateLevel_2(input wire A, B, C, output wire Y);

  wire notA, notB, notC, or1, or2;

  // Not's 
  
  not (Y, B);
  
endmodule

// Ejercicio 2 Tabla 2;

module gateLevel_3(input wire A, B, C, output wire Y);

  wire notA, notB, notC, or1, or2;

  // Not's 
  
  not (notB, B);
  
  // Or's
  
  or  (Y, notB, C);
    
endmodule

// Ejercicio 2 Tabla 4;

module gateLevel_4(input wire A, B, C, output wire Y);

  wire notA, notB, notC, or1, or2;

  // Not's 
  
  not (notA, A);
  not (notC, C);
  
  // Or's
  
  or  (or1, notA, B);
  or  (or2, B, notC);
  
  // And's
  
  and (Y, or1, or2);
  
endmodule


// Ejercicio 1 Tabla 3
module operadores_1(input wire A, B, C, D, output wire Y);

  assign Y = (~A & ~B & ~C & ~D) | (~A & ~B & C & D) | (~A & B & ~C & D) | (~A & B & C & ~D) | (A & B & ~C & ~D) | (A & B & C & D) | (A & ~B & ~C & D) | (A & ~B & C & ~D);

endmodule

// Ejercicio 1 Tabla 4
module operadores_2(input wire A, B, C, D, output wire Y);

  assign Y = A & (~A | B | C | ~D);

endmodule

// Ejercicio 2 Tabla 1
module operadores_3(input wire A, B, C, D, output wire Y);

  assign Y = (~B & ~C & ~D) | (A & ~C) | (A & ~B) | (A & C & ~D);

endmodule

// Ejercicio 2 Tabla 3
module operadores_4(input wire A, B, C, D, output wire Y);

  assign Y = (B | D) & (A | B | ~C);
  
endmodule

Test_Bench_tb.v
// Esto es para aquellos que están usando iverilog de compilador
// Para los que usan apio pueden obviarlo
`include "codigo.v"
// ` -> backtick
// ' -> comilla simple


module testbench();

  // Inputs para Gate_Level
  reg p1, p2, p3, p4, p5, p6;
  // Inputs para Operators
  reg i1, i2, i3, i4, i5, i6, i7, i8;
  
  // Outputs para Gate_Level
  wire led1, led2, led3, led4;
  // Outputs para Operators
  wire led5, led6, led7, led8;

  gateLevel_1   G1(p1, p2, p3, led1);
  gateLevel_2   G2(p1, p2, p3, led2);
  gateLevel_3   G3(p4, p5, p6, led3);
  gateLevel_4   G4(p4, p5, p6, led4);
  
  
  operadores_1 OP1(i1, i2, i3, i4, led5);
  operadores_2 OP2(i1, i2, i3, i4, led6);
  operadores_3 OP3(i5, i6, i7, i8, led7);
  operadores_4 OP4(i5, i6, i7, i8, led8);

  
  // Gate Level Modelling --> Ejercicio 1: Tablas 1 y 2 
  initial begin
	#1
    $display("Ejercicio 1: Tablas 1 y 2");
    $display("A B C | Y1 Y2");
    $display("------|------");
    $monitor("%b %b %b | %b  %b", p1, p2, p3, led1, led2);
       p1 = 0; p2 = 0; p3 = 0;
    #1 p1 = 0; p2 = 0; p3 = 1;
    #1 p1 = 0; p2 = 1; p3 = 0;
    #1 p1 = 0; p2 = 1; p3 = 1;
    #1 p1 = 1; p2 = 0; p3 = 0;
    #1 p1 = 1; p2 = 0; p3 = 1;
    #1 p1 = 1; p2 = 1; p3 = 0;
    #1 p1 = 1; p2 = 1; p3 = 1;
  end
  
  // Gate Level Modelling --> Ejercicio 2: Tablas 2 y 4
  initial begin
    #10
    $display("\n");
	$display("Ejercicio 2: Tablas 2 y 4");
    $display("A B C | Y1 Y2");
    $display("------|--");
    $monitor("%b %b %b | %b %b", p4, p5, p6, led3, led4);
       p4 = 0; p5 = 0; p6 = 0;
    #1 p4 = 0; p5 = 0; p6 = 1;
    #1 p4 = 0; p5 = 1; p6 = 0;
    #1 p4 = 0; p5 = 1; p6 = 1;
    #1 p4 = 1; p5 = 0; p6 = 0;
    #1 p4 = 1; p5 = 0; p6 = 1;
    #1 p4 = 1; p5 = 1; p6 = 0;
    #1 p4 = 1; p5 = 1; p6 = 1;
  end
  
  // Operators --> Ejercicio 1: Tablas 3 y 4
  initial begin
	#18
	$display("\n");
    $display("Ejercicio 1: Tablas 3 y 4");
    $display("A B C D | Y1 Y2");
    $display("--------|------");
    $monitor("%b %b %b %b | %b  %b", i1, i2, i3, i4, led5, led6);
       i1 = 0; i2 = 0; i3 = 0; i4 = 0;
    #1 i1 = 0; i2 = 0; i3 = 0; i4 = 1;
    #1 i1 = 0; i2 = 0; i3 = 1; i4 = 0;
    #1 i1 = 0; i2 = 0; i3 = 1; i4 = 1;
    #1 i1 = 0; i2 = 1; i3 = 0; i4 = 0;
    #1 i1 = 0; i2 = 1; i3 = 0; i4 = 1;
    #1 i1 = 0; i2 = 1; i3 = 1; i4 = 0;
    #1 i1 = 0; i2 = 1; i3 = 1; i4 = 1;
	#1 i1 = 1; i2 = 0; i3 = 0; i4 = 0;
    #1 i1 = 1; i2 = 0; i3 = 0; i4 = 1;
    #1 i1 = 1; i2 = 0; i3 = 1; i4 = 0;
    #1 i1 = 1; i2 = 0; i3 = 1; i4 = 1;
    #1 i1 = 1; i2 = 1; i3 = 0; i4 = 0;
    #1 i1 = 1; i2 = 1; i3 = 0; i4 = 1;
    #1 i1 = 1; i2 = 1; i3 = 1; i4 = 0;
    #1 i1 = 1; i2 = 1; i3 = 1; i4 = 1;
  end
  
  // Gate Level Modelling --> Ejercicio 2: Tablas 2 y 4
  initial begin
    #35
    $display("\n");
	$display("Ejercicio 2: Tablas 1 y 3");
    $display("A B C D | Y1 Y2");
    $display("--------|------");
    $monitor("%b %b %b %b | %b  %b", i5, i6, i7, i8, led7, led8);
       i5 = 0; i6 = 0; i7 = 0; i8 = 0;
    #1 i5 = 0; i6 = 0; i7 = 0; i8 = 1;
    #1 i5 = 0; i6 = 0; i7 = 1; i8 = 0;
    #1 i5 = 0; i6 = 0; i7 = 1; i8 = 1;
    #1 i5 = 0; i6 = 1; i7 = 0; i8 = 0;
    #1 i5 = 0; i6 = 1; i7 = 0; i8 = 1;
    #1 i5 = 0; i6 = 1; i7 = 1; i8 = 0;
    #1 i5 = 0; i6 = 1; i7 = 1; i8 = 1;
	#1 i5 = 1; i6 = 0; i7 = 0; i8 = 0;
    #1 i5 = 1; i6 = 0; i7 = 0; i8 = 1;
    #1 i5 = 1; i6 = 0; i7 = 1; i8 = 0;
    #1 i5 = 1; i6 = 0; i7 = 1; i8 = 1;
    #1 i5 = 1; i6 = 1; i7 = 0; i8 = 0;
    #1 i5 = 1; i6 = 1; i7 = 0; i8 = 1;
    #1 i5 = 1; i6 = 1; i7 = 1; i8 = 0;
    #1 i5 = 1; i6 = 1; i7 = 1; i8 = 1;
  end
  
  initial
    #52 $finish;
  
  initial begin
    $dumpfile("Test_Bench_tb.vcd");
    $dumpvars(0, testbench);
  end
  
endmodule

Test_Bench_tb.vcd
$date
	Sat Aug 08 21:06:29 2020
$end
$version
	Icarus Verilog
$end
$timescale
	1s
$end
$scope module testbench $end
$var wire 1 ! led8 $end
$var wire 1 " led7 $end
$var wire 1 # led6 $end
$var wire 1 $ led5 $end
$var wire 1 % led4 $end
$var wire 1 & led3 $end
$var wire 1 ' led2 $end
$var wire 1 ( led1 $end
$var reg 1 ) i1 $end
$var reg 1 * i2 $end
$var reg 1 + i3 $end
$var reg 1 , i4 $end
$var reg 1 - i5 $end
$var reg 1 . i6 $end
$var reg 1 / i7 $end
$var reg 1 0 i8 $end
$var reg 1 1 p1 $end
$var reg 1 2 p2 $end
$var reg 1 3 p3 $end
$var reg 1 4 p4 $end
$var reg 1 5 p5 $end
$var reg 1 6 p6 $end
$scope module G1 $end
$var wire 1 1 A $end
$var wire 1 2 B $end
$var wire 1 3 C $end
$var wire 1 ( Y $end
$var wire 1 7 notA $end
$var wire 1 8 notB $end
$var wire 1 9 notC $end
$var wire 1 : or1 $end
$var wire 1 ; or2 $end
$upscope $end
$scope module G2 $end
$var wire 1 1 A $end
$var wire 1 2 B $end
$var wire 1 3 C $end
$var wire 1 ' Y $end
$upscope $end
$scope module G3 $end
$var wire 1 4 A $end
$var wire 1 5 B $end
$var wire 1 6 C $end
$var wire 1 & Y $end
$var wire 1 < notB $end
$upscope $end
$scope module G4 $end
$var wire 1 4 A $end
$var wire 1 5 B $end
$var wire 1 6 C $end
$var wire 1 % Y $end
$var wire 1 = notA $end
$var wire 1 > notC $end
$var wire 1 ? or1 $end
$var wire 1 @ or2 $end
$upscope $end
$scope module OP1 $end
$var wire 1 ) A $end
$var wire 1 * B $end
$var wire 1 + C $end
$var wire 1 , D $end
$var wire 1 $ Y $end
$upscope $end
$scope module OP2 $end
$var wire 1 ) A $end
$var wire 1 * B $end
$var wire 1 + C $end
$var wire 1 , D $end
$var wire 1 # Y $end
$upscope $end
$scope module OP3 $end
$var wire 1 - A $end
$var wire 1 . B $end
$var wire 1 / C $end
$var wire 1 0 D $end
$var wire 1 " Y $end
$upscope $end
$scope module OP4 $end
$var wire 1 - A $end
$var wire 1 . B $end
$var wire 1 / C $end
$var wire 1 0 D $end
$var wire 1 ! Y $end
$upscope $end
$upscope $end
$enddefinitions $end
#0
$dumpvars
x@
x?
x>
x=
x<
x;
x:
x9
x8
x7
x6
x5
x4
x3
x2
x1
x0
x/
x.
x-
x,
x+
x*
x)
x(
x'
x&
x%
x$
x#
x"
x!
$end
#1
1(
1:
19
1;
18
1'
17
03
02
01
#2
0(
0:
09
13
#3
1(
1:
19
08
0'
03
12
#4
0(
0:
09
13
#5
1(
19
18
1'
07
1:
03
02
11
#6
09
13
#7
0(
19
0;
08
0'
03
12
#8
1(
09
1;
13
#10
1%
1@
1&
1>
1<
1?
1=
06
05
04
#11
0%
0@
0>
16
#12
1%
0&
1>
0<
1@
06
15
#13
1&
0>
16
#14
0%
1>
1<
0?
1@
0=
06
05
14
#15
0@
0>
16
#16
1%
0&
1>
0<
1?
1@
06
15
#17
1&
0>
16
#18
1$
0#
0,
0+
0*
0)
#19
0$
1,
#20
0,
1+
#21
1$
1,
#22
0$
0,
0+
1*
#23
1$
1,
#24
0,
1+
#25
0$
1,
#26
1#
0,
0+
0*
1)
#27
1$
0#
1,
#28
1#
0,
1+
#29
0$
1,
#30
1$
0,
0+
1*
#31
0$
1,
#32
0,
1+
#33
1$
1,
#35
1"
0!
00
0/
0.
0-
#36
0"
1!
10
#37
0!
00
1/
#38
10
#39
1!
00
0/
1.
#40
10
#41
00
1/
#42
10
#43
1"
0!
00
0/
0.
1-
#44
1!
10
#45
0!
00
1/
#46
1!
10
#47
1"
00
0/
1.
#48
10
#49
00
1/
#50
0"
10
