Nibbler/Prueba/uP.v
//-----------------------------------
// Ricardo Pellecer Orellana
// Carné: 19072
// 22/Noviembre/2020
// -----------------------------------

//Program Counter - Sí funciona
module Counter (input wire clock, reset, load, enable, input wire [11:0]load_data, output reg [11:0]value);
  always @ (posedge clock, posedge reset, load) begin
    if (reset) begin
      value <= 12'b0;
    end
    else if (load) begin
      value <= load_data;
    end
    else if (enable) begin
      value <= value + 1;
    end
  end
endmodule

//ROM - Sí funciona
module ROM_Memory (input wire [11:0]address, output wire [7:0]opcode);
  reg [7:0] ROM [0:4095];
  initial begin
      $readmemh("instructions.list", ROM);
  end
  assign opcode = ROM[address];
endmodule

// Flip Flop Tipo D --> para fetch
module flip_flop8 (input wire clk, reset, enable, input wire [7:0]d, output reg [7:0]q);
	always @ (posedge clk or posedge reset or enable)begin
		if (reset) begin
			q <= 8'b0;
		end
    else if (enable) begin
      q <= d;
    end
	end
endmodule

//Fetch - Sí funciona
module Fetch (input wire clk, reset, enable, input wire [7:0]opcode, output wire [3:0]instruction, operand);
  wire [7:0]q;
  assign instruction = q[7:4];
  assign operand = q[3:0];
  flip_flop8 F1(clk, reset, enable, opcode, q);
endmodule

// Flip Flop Tipo D --> para flags - Sí funciona
module Flags (input wire clk, reset, enable, input wire [1:0]d, output reg [1:0]q);
	always @ (posedge clk or posedge reset or enable)begin
		if (reset) begin
			q <= 2'b0;
		end
    else if (enable) begin
      q <= d;
    end
	end
endmodule

// Flip Flop Tipo D --> para toggle del phase
module flip_flop1 (input wire clk, reset, enable, input wire d, output reg q);
	always @ (posedge clk or posedge reset or enable)begin
		if (reset) begin
			q <= 1'b0;
		end
    else if (enable) begin
      q <= d;
    end
	end
endmodule

// Flip Flop Toggle --> para phase - Sí funciona
module Phase (input wire clk, reset, enable, output wire q);
  wire d;
  assign d = ~q;
	flip_flop1 F1(clk, reset, enable, d, q);
endmodule

//Decode
module Microcode(input wire [6:0]address, output reg [12:0]control);
  always @ (address) begin
    casex (address)
    7'bxxxxxx0: //0
      control <= 13'b1000000001000;
    7'b00001x1: //1
      control <= 13'b0100000001000;
    7'b00000x1: //2
      control <= 13'b1000000001000;
    7'b00011x1: //3
      control <= 13'b1000000001000;
    7'b00010x1: //4
      control <= 13'b0100000001000;
    7'b0010xx1: //5
      control <= 13'b0001001000010;
    7'b0011xx1: //6
      control <= 13'b1001001100000;
    7'b0100xx1: //7
      control <= 13'b0011010000010;
    7'b0101xx1: //8
      control <= 13'b0011010000100;
    7'b0110xx1: //9
      control <= 13'b1011010100000;
    7'b0111xx1: //10
      control <= 13'b1000000111000;
    7'b1000x11: //11
      control <= 13'b0100000001000;
    7'b1000x01: //12
      control <= 13'b1000000001000;
    7'b1001x11: //13
      control <= 13'b1000000001000;
    7'b1001x01: //14
      control <= 13'b0100000001000;
    7'b1010xx1: //15
      control <= 13'b0011011000010;
    7'b1011xx1: //16
      control <= 13'b1011011100000;
    7'b1100xx1: //17
      control <= 13'b0100000001000;
    7'b1101xx1: //18
      control <= 13'b0000000001001;
    7'b1110xx1: //19
      control <= 13'b0011100000010;
    7'b1111xx1: //20
      control <= 13'b1011100100000;
    default:
      control <= 13'b1111111111111;
    endcase
  end
endmodule

// Buffer Tri-estado - Sí funciona
module Tris (input wire enable, input wire [3:0]in, output wire [3:0]out);
  assign out = enable ? in:4'bz;
endmodule

//RAM
module RAM_Memory (input wire enable, write, read, input wire [11:0]address_RAM, inout [3:0]data);
  reg [3:0] RAM [0:4095];
  reg [3:0]data_out;

  //Coloca un tris para poder escribir o leer
  assign data = (enable & read & ~write) ? data_out:4'bz;
  //Bloque de escritura
  always @ ( address_RAM or data or enable or write ) begin
    if (enable && write) begin
      RAM[address_RAM] = data;
    end
  end
  //Bloque de lectura
  always @ ( address_RAM or enable or write or read) begin
    if (enable && ~write && read) begin
      data_out = RAM[address_RAM];
    end
  end
endmodule

// Flip Flop Tipo D - Sí funciona
module Accumulator (input wire clk, reset, enable, input wire [3:0]result, output reg [3:0]accu);
	always @ (posedge clk or posedge reset or enable) begin
		if (reset) begin
			accu <= 4'b0;
		end
    else if (enable) begin
      accu <= result;
    end
	end
endmodule

//ALU - Los 3 bits de seleccion vienen del microcode el databus es el operand y la accu es W
module ALU (input wire [3:0]data_bus, accu, input wire [2:0]selector, output reg [3:0]result, output wire [1:0]flags);
  wire zero;
  reg carry;
  always @ ( * ) begin
    case (selector)
    0:
      {carry, result} <= accu;
    1:
      {carry, result} <= accu - data_bus;
    2:
      {carry, result} <= data_bus;
    3:
      {carry, result} <= accu + data_bus;
    4:
      {carry, result} <= accu ~& data_bus;
    default:
      {carry, result} <= 5'b0;
    endcase
  end
  assign zero = ((result == 4'b0) && (carry == 1'b0)) ? 1'b1:1'b0;
  assign flags[0] = zero;
  assign flags[1] = carry;
endmodule

// Flip Flop Tipo D --> para outputs
module Outputs (input wire clk, reset, enable, input wire [3:0]d, output reg [3:0]q);
	always @ (posedge clk or posedge reset or enable)begin
		if (reset) begin
			q <= 4'b0;
		end
    else if (enable) begin
      q <= d;
    end
	end
endmodule

//Nibbler
module uP (input wire clock, reset, input wire [3:0]pushbuttons, output wire phase, c_flag, z_flag, output wire [3:0]instr, oprnd, data_bus, FF_out, accu, output wire [7:0]program_byte, output wire [11:0]PC, address_RAM);
  //Cables internos del Nibbler
  wire [1:0]flags_in, flags_out; //posicion 1 es carry y 0 es zero
  wire [12:0]control;
  wire [3:0]alu_result;
  wire [6:0]address;
  //Defino a address como la contatenacion de varias entradas
  assign address = {instr, c_flag, z_flag, phase};
  //address_RAM
  assign address_RAM = {oprnd, program_byte};
  //Defino mis banderas concatenadas
  assign c_flag = flags_out[1];
  assign z_flag = flags_out[0];
  //Defino a los bits de control con mi address a traves del decode
  Microcode M1(address, control);
  //Doy valor al PC a traves de las señales de control 11 y 12 -load y enable respectivamente-
  Counter PC1(clock, reset, control[11], control[12], address_RAM, PC);
  //Busco la instruccion correspondiente en la ROM con el PC
  ROM_Memory ROM1(PC, program_byte);
  //Fetch divide al program_byte -opcode- en instruccion y operando
  Fetch FE1(clock, reset, ~phase, program_byte, instr, oprnd);
  //Uso el toggle para definir el phase
  Phase PH1(clock, reset, 1'b1, phase); //Enable del phase siempre en 1?????
  //Dejo pasar mis banderas con el bit 9 de control -LoadFlags-
  Flags FL1(clock, reset, control[9], flags_in, flags_out);
  //Primer Bus Driver - Defino a data_bus usando el bit 1 de control -oeOprnd-
  Tris BD1(control[1], oprnd, data_bus);
  //Operaciones con ALU entra data_bus y accu, selecciono con los bits 6, 7 y 8 de control, sale el resultado y las banderas
  ALU A1(data_bus, accu, control[8:6], alu_result, flags_in);
  //Genero el registro W - Defino a accu a traves del resultado de la ALU y del bit 10 de control -loadA-
  Accumulator A2(clock, reset, control[10], alu_result, accu);
  //Segundo Bus Driver - Defino a data_bus usando el bit 3 de control -oeALU-
  Tris BD2(control[3], alu_result, data_bus);
  //Definicion de la RAM uso de control 4 y 5 -weRAM y csRAM respectivamente-
  RAM_Memory RAM1(control[5], control[4], control[5], address_RAM, data_bus); //output enable de la RAM es cuando los otros tres tris estan en cero????
  //Tercer Bus Driver - Defino a data_bus usando el bit 2 de control -oeIN-
  Tris BD3(control[2], pushbuttons, data_bus);
  //Flip flop para Outputs con bit 0 de control -loadOut-
  Outputs O1(clock, reset, control[0], data_bus, FF_out);
endmodule

Nibbler/Prueba/uP_tb.v
module testbench();

    reg clock, reset;
    reg [3:0] pushbuttons;
    wire phase, c_flag, z_flag;
    wire [3:0] instr, oprnd, accu, data_bus, FF_out;
    wire [7:0] program_byte;
    wire [11:0] PC, address_RAM;

    integer nota = 0;

    uP uPmodule(.clock(clock),
                .reset(reset),
                .pushbuttons(pushbuttons),
                .phase(phase),
                .c_flag(c_flag),
                .z_flag(z_flag),
                .instr(instr),
                .oprnd(oprnd),
                .accu(accu),
                .data_bus(data_bus),
                .FF_out(FF_out),
                .program_byte(program_byte),
                .PC(PC),
                .address_RAM(address_RAM));

    initial
        #500 $finish;

    initial begin
        #84
        $display("PC: %h\taccu: %h",PC,accu);
        if (PC === 12'h124 && accu === 4'h4) begin
            nota = nota + 5;
            $display("ADDI funciona bien. Su nota es: %d", nota);
        end
        else
            $display("ADDI NO funciona bien. Su nota es: %d", nota);
    end

    always
        #5 clock = ~clock;

    initial begin
        clock = 0; reset = 0; pushbuttons = 4'b0110; nota = 0;
        #2 reset = 1;
        #1 reset = 0;
    end



    initial begin
        $dumpfile("uP_tb.vcd");
        $dumpvars(0, testbench);
    end

endmodule

Nibbler/Prueba/uP_tb.vcd
$date
	Mon Nov 16 17:58:59 2020
$end
$version
	Icarus Verilog
$end
$timescale
	1ps
$end
$scope module testbench $end
$var wire 4 ! data_bus [3:0] $end
$var wire 1 " z_flag $end
$var wire 8 # program_byte [7:0] $end
$var wire 1 $ phase $end
$var wire 4 % oprnd [3:0] $end
$var wire 4 & instr [3:0] $end
$var wire 1 ' c_flag $end
$var wire 12 ( address_RAM [11:0] $end
$var wire 4 ) accu [3:0] $end
$var wire 12 * PC [11:0] $end
$var wire 4 + FF_out [3:0] $end
$var reg 1 , clock $end
$var reg 4 - pushbuttons [3:0] $end
$var reg 1 . reset $end
$var integer 32 / nota [31:0] $end
$scope module uPmodule $end
$var wire 1 , clock $end
$var wire 4 0 data_bus [3:0] $end
$var wire 4 1 pushbuttons [3:0] $end
$var wire 1 . reset $end
$var wire 1 " z_flag $end
$var wire 8 2 program_byte [7:0] $end
$var wire 1 $ phase $end
$var wire 4 3 oprnd [3:0] $end
$var wire 4 4 instr [3:0] $end
$var wire 2 5 flags_out [1:0] $end
$var wire 2 6 flags_in [1:0] $end
$var wire 13 7 control [12:0] $end
$var wire 1 ' c_flag $end
$var wire 4 8 alu_result [3:0] $end
$var wire 12 9 address_RAM [11:0] $end
$var wire 7 : address [6:0] $end
$var wire 4 ; accu [3:0] $end
$var wire 12 < PC [11:0] $end
$var wire 4 = FF_out [3:0] $end
$scope module A1 $end
$var wire 4 > data_bus [3:0] $end
$var wire 3 ? selector [2:0] $end
$var wire 1 @ zero $end
$var wire 2 A flags [1:0] $end
$var wire 4 B accu [3:0] $end
$var reg 1 C carry $end
$var reg 4 D result [3:0] $end
$upscope $end
$scope module A2 $end
$var wire 1 , clk $end
$var wire 1 E enable $end
$var wire 1 . reset $end
$var wire 4 F result [3:0] $end
$var reg 4 G accu [3:0] $end
$upscope $end
$scope module BD1 $end
$var wire 1 H enable $end
$var wire 4 I out [3:0] $end
$var wire 4 J in [3:0] $end
$upscope $end
$scope module BD2 $end
$var wire 1 K enable $end
$var wire 4 L in [3:0] $end
$var wire 4 M out [3:0] $end
$upscope $end
$scope module BD3 $end
$var wire 1 N enable $end
$var wire 4 O in [3:0] $end
$var wire 4 P out [3:0] $end
$upscope $end
$scope module FE1 $end
$var wire 1 , clk $end
$var wire 1 Q enable $end
$var wire 1 . reset $end
$var wire 8 R q [7:0] $end
$var wire 4 S operand [3:0] $end
$var wire 8 T opcode [7:0] $end
$var wire 4 U instruction [3:0] $end
$scope module F1 $end
$var wire 1 , clk $end
$var wire 1 Q enable $end
$var wire 1 . reset $end
$var wire 8 V d [7:0] $end
$var reg 8 W q [7:0] $end
$upscope $end
$upscope $end
$scope module FL1 $end
$var wire 1 , clk $end
$var wire 2 X d [1:0] $end
$var wire 1 Y enable $end
$var wire 1 . reset $end
$var reg 2 Z q [1:0] $end
$upscope $end
$scope module M1 $end
$var wire 7 [ address [6:0] $end
$var reg 13 \ control [12:0] $end
$upscope $end
$scope module O1 $end
$var wire 1 , clk $end
$var wire 4 ] d [3:0] $end
$var wire 1 ^ enable $end
$var wire 1 . reset $end
$var reg 4 _ q [3:0] $end
$upscope $end
$scope module PC1 $end
$var wire 1 , clock $end
$var wire 1 ` enable $end
$var wire 1 a load $end
$var wire 12 b load_data [11:0] $end
$var wire 1 . reset $end
$var reg 12 c value [11:0] $end
$upscope $end
$scope module PH1 $end
$var wire 1 , clk $end
$var wire 1 d d $end
$var wire 1 e enable $end
$var wire 1 . reset $end
$var wire 1 $ q $end
$scope module F1 $end
$var wire 1 , clk $end
$var wire 1 d d $end
$var wire 1 e enable $end
$var wire 1 . reset $end
$var reg 1 $ q $end
$upscope $end
$upscope $end
$scope module RAM1 $end
$var wire 12 f address_RAM [11:0] $end
$var wire 4 g data [3:0] $end
$var wire 1 h enable $end
$var wire 1 i read $end
$var wire 1 j write $end
$var reg 4 k data_out [3:0] $end
$upscope $end
$scope module ROM1 $end
$var wire 12 l address [11:0] $end
$var wire 8 m opcode [7:0] $end
$upscope $end
$upscope $end
$upscope $end
$enddefinitions $end
#0
$dumpvars
bx m
bx l
bx k
xj
xi
xh
bx g
bx f
1e
xd
bx c
bx b
xa
x`
bx _
x^
bx ]
bx \
bx [
bx Z
xY
bx X
bx W
bx V
bx U
bx T
bx S
bx R
xQ
bx P
b110 O
xN
bx M
bx L
xK
bx J
bx I
xH
bx G
bx F
xE
bx D
xC
bx B
bx A
x@
bx ?
bx >
bx =
bx <
bx ;
bx :
bx 9
bx 8
bx 7
bx 6
bx 5
bx 4
bx 3
bx 2
b110 1
bx 0
b0 /
0.
b110 -
0,
bx +
bx *
bx )
bx (
x'
bx &
bx %
x$
bx #
x"
bx !
$end
#2
b0 !
b0 0
b0 >
b0 I
b0 M
b0 P
b0 ]
b0 g
1@
0^
0N
0i
0j
0h
1K
0E
b0 ?
0H
0Y
1`
0a
b1 6
b1 A
b1 X
0C
b0 8
b0 D
b0 F
b0 L
b1000000001000 7
b1000000001000 \
b0 %
b0 3
b0 J
b0 S
b0 &
b0 4
b0 U
0"
0'
1d
1Q
b0 )
b0 ;
b0 B
b0 G
b0 R
b0 W
b0 5
b0 Z
b0 +
b0 =
b0 _
b1001111 (
b1001111 9
b1001111 b
b1001111 f
b1001111 #
b1001111 2
b1001111 T
b1001111 V
b1001111 m
b0 *
b0 <
b0 c
b0 l
b0 :
b0 [
0$
1.
#3
0.
#5
b0 6
b0 A
b0 X
0@
1"
b1111 8
b1111 D
b1111 F
b1111 L
b1 5
b1 Z
b1111 !
b1111 0
b1111 >
b1111 I
b1111 M
b1111 P
b1111 ]
b1111 g
0K
1E
b10 ?
1H
1Y
0`
b11010000010 7
b11010000010 \
b1111 %
b1111 3
b1111 J
b1111 S
b100 &
b100 4
b100 U
0d
0Q
b1001111 R
b1001111 W
b111101000011 (
b111101000011 9
b111101000011 b
b111101000011 f
b1000011 #
b1000011 2
b1000011 T
b1000011 V
b1000011 m
b1 *
b1 <
b1 c
b1 l
b100011 :
b100011 [
1$
1,
#10
0,
#15
b1111 !
b1111 0
b1111 >
b1111 I
b1111 M
b1111 P
b1111 ]
b1111 g
b1101000011 (
b1101000011 9
b1101000011 b
b1101000011 f
b11 %
b11 3
b11 J
b11 S
1K
0E
b0 ?
0H
0Y
1`
b1000011 R
b1000011 W
b1000000001000 7
b1000000001000 \
0"
1d
1Q
b1111 )
b1111 ;
b1111 B
b1111 G
b0 5
b0 Z
b100000 :
b100000 [
0$
1,
#20
0,
#25
b11 8
b11 D
b11 F
b11 L
b11 !
b11 0
b11 >
b11 I
b11 M
b11 P
b11 ]
b11 g
0K
1E
b10 ?
1H
1Y
0`
b11010000010 7
b11010000010 \
0d
0Q
b1111000001 (
b1111000001 9
b1111000001 b
b1111000001 f
b11000001 #
b11000001 2
b11000001 T
b11000001 V
b11000001 m
b10 *
b10 <
b10 c
b10 l
b100001 :
b100001 [
1$
1,
#30
0,
#35
b11 !
b11 0
b11 >
b11 I
b11 M
b11 P
b11 ]
b11 g
b111000001 (
b111000001 9
b111000001 b
b111000001 f
b1 %
b1 3
b1 J
b1 S
b1100 &
b1100 4
b1100 U
1K
0E
b0 ?
0H
0Y
1`
b11000001 R
b11000001 W
b1000000001000 7
b1000000001000 \
1d
1Q
b11 )
b11 ;
b11 B
b11 G
b1100000 :
b1100000 [
0$
1,
#40
0,
#45
0`
1a
b100000001000 7
b100000001000 \
0d
0Q
b110100001 (
b110100001 9
b110100001 b
b110100001 f
b10100001 #
b10100001 2
b10100001 T
b10100001 V
b10100001 m
b100100011 *
b100100011 <
b100100011 c
b100100011 l
b1100001 :
b1100001 [
1$
1,
#50
0,
#55
bx %
bx 3
bx J
bx S
bx &
bx 4
bx U
1`
0a
bx R
bx W
b1000000001000 7
b1000000001000 \
1d
1Q
bx (
bx 9
bx b
bx f
bx #
bx 2
bx T
bx V
bx m
b110100010 *
b110100010 <
b110100010 c
b110100010 l
bx000 :
bx000 [
0$
1,
#60
0,
#65
0d
0Q
b110100011 *
b110100011 <
b110100011 c
b110100011 l
bx001 :
bx001 [
1$
1,
#70
0,
#75
1d
1Q
b110100100 *
b110100100 <
b110100100 c
b110100100 l
bx000 :
bx000 [
0$
1,
#80
0,
#85
0d
0Q
b110100101 *
b110100101 <
b110100101 c
b110100101 l
bx001 :
bx001 [
1$
1,
#90
0,
#95
1d
1Q
b110100110 *
b110100110 <
b110100110 c
b110100110 l
bx000 :
bx000 [
0$
1,
#100
0,
#105
0d
0Q
b110100111 *
b110100111 <
b110100111 c
b110100111 l
bx001 :
bx001 [
1$
1,
#110
0,
#115
1d
1Q
b110101000 *
b110101000 <
b110101000 c
b110101000 l
bx000 :
bx000 [
0$
1,
#120
0,
#125
0d
0Q
b110101001 *
b110101001 <
b110101001 c
b110101001 l
bx001 :
bx001 [
1$
1,
#130
0,
#135
1d
1Q
b110101010 *
b110101010 <
b110101010 c
b110101010 l
bx000 :
bx000 [
0$
1,
#140
0,
#145
0d
0Q
b110101011 *
b110101011 <
b110101011 c
b110101011 l
bx001 :
bx001 [
1$
1,
#150
0,
#155
1d
1Q
b110101100 *
b110101100 <
b110101100 c
b110101100 l
bx000 :
bx000 [
0$
1,
#160
0,
#165
0d
0Q
b110101101 *
b110101101 <
b110101101 c
b110101101 l
bx001 :
bx001 [
1$
1,
#170
0,
#175
1d
1Q
b110101110 *
b110101110 <
b110101110 c
b110101110 l
bx000 :
bx000 [
0$
1,
#180
0,
#185
0d
0Q
b110101111 *
b110101111 <
b110101111 c
b110101111 l
bx001 :
bx001 [
1$
1,
#190
0,
#195
1d
1Q
b110110000 *
b110110000 <
b110110000 c
b110110000 l
bx000 :
bx000 [
0$
1,
#200
0,
#205
0d
0Q
b110110001 *
b110110001 <
b110110001 c
b110110001 l
bx001 :
bx001 [
1$
1,
#210
0,
#215
1d
1Q
b110110010 *
b110110010 <
b110110010 c
b110110010 l
bx000 :
bx000 [
0$
1,
#220
0,
#225
0d
0Q
b110110011 *
b110110011 <
b110110011 c
b110110011 l
bx001 :
bx001 [
1$
1,
#230
0,
#235
1d
1Q
b110110100 *
b110110100 <
b110110100 c
b110110100 l
bx000 :
bx000 [
0$
1,
#240
0,
#245
0d
0Q
b110110101 *
b110110101 <
b110110101 c
b110110101 l
bx001 :
bx001 [
1$
1,
#250
0,
#255
1d
1Q
b110110110 *
b110110110 <
b110110110 c
b110110110 l
bx000 :
bx000 [
0$
1,
#260
0,
#265
0d
0Q
b110110111 *
b110110111 <
b110110111 c
b110110111 l
bx001 :
bx001 [
1$
1,
#270
0,
#275
1d
1Q
b110111000 *
b110111000 <
b110111000 c
b110111000 l
bx000 :
bx000 [
0$
1,
#280
0,
#285
0d
0Q
b110111001 *
b110111001 <
b110111001 c
b110111001 l
bx001 :
bx001 [
1$
1,
#290
0,
#295
1d
1Q
b110111010 *
b110111010 <
b110111010 c
b110111010 l
bx000 :
bx000 [
0$
1,
#300
0,
#305
0d
0Q
b110111011 *
b110111011 <
b110111011 c
b110111011 l
bx001 :
bx001 [
1$
1,
#310
0,
#315
1d
1Q
b110111100 *
b110111100 <
b110111100 c
b110111100 l
bx000 :
bx000 [
0$
1,
#320
0,
#325
0d
0Q
b110111101 *
b110111101 <
b110111101 c
b110111101 l
bx001 :
bx001 [
1$
1,
#330
0,
#335
1d
1Q
b110111110 *
b110111110 <
b110111110 c
b110111110 l
bx000 :
bx000 [
0$
1,
#340
0,
#345
0d
0Q
b110111111 *
b110111111 <
b110111111 c
b110111111 l
bx001 :
bx001 [
1$
1,
#350
0,
#355
1d
1Q
b111000000 *
b111000000 <
b111000000 c
b111000000 l
bx000 :
bx000 [
0$
1,
#360
0,
#365
0d
0Q
b111000001 *
b111000001 <
b111000001 c
b111000001 l
bx001 :
bx001 [
1$
1,
#370
0,
#375
1d
1Q
b111000010 *
b111000010 <
b111000010 c
b111000010 l
bx000 :
bx000 [
0$
1,
#380
0,
#385
0d
0Q
b111000011 *
b111000011 <
b111000011 c
b111000011 l
bx001 :
bx001 [
1$
1,
#390
0,
#395
1d
1Q
b111000100 *
b111000100 <
b111000100 c
b111000100 l
bx000 :
bx000 [
0$
1,
#400
0,
#405
0d
0Q
b111000101 *
b111000101 <
b111000101 c
b111000101 l
bx001 :
bx001 [
1$
1,
#410
0,
#415
1d
1Q
b111000110 *
b111000110 <
b111000110 c
b111000110 l
bx000 :
bx000 [
0$
1,
#420
0,
#425
0d
0Q
b111000111 *
b111000111 <
b111000111 c
b111000111 l
bx001 :
bx001 [
1$
1,
#430
0,
#435
1d
1Q
b111001000 *
b111001000 <
b111001000 c
b111001000 l
bx000 :
bx000 [
0$
1,
#440
0,
#445
0d
0Q
b111001001 *
b111001001 <
b111001001 c
b111001001 l
bx001 :
bx001 [
1$
1,
#450
0,
#455
1d
1Q
b111001010 *
b111001010 <
b111001010 c
b111001010 l
bx000 :
bx000 [
0$
1,
#460
0,
#465
0d
0Q
b111001011 *
b111001011 <
b111001011 c
b111001011 l
bx001 :
bx001 [
1$
1,
#470
0,
#475
1d
1Q
b111001100 *
b111001100 <
b111001100 c
b111001100 l
bx000 :
bx000 [
0$
1,
#480
0,
#485
0d
0Q
b111001101 *
b111001101 <
b111001101 c
b111001101 l
bx001 :
bx001 [
1$
1,
#490
0,
#495
1d
1Q
b111001110 *
b111001110 <
b111001110 c
b111001110 l
bx000 :
bx000 [
0$
1,
