Nibbler/Prueba/uP.v
//-----------------------------------
// Ricardo Pellecer Orellana
// Carné: 19072
// 22/Noviembre/2020
// -----------------------------------

//Program Counter - Sí funciona
module Counter (input wire clock, reset, load, enable, input wire [11:0]load_data, output reg [11:0]value);
  always @ (posedge clock, posedge reset, load) begin
    if (reset) begin
      value <= 12'b0;
    end
    else if (load) begin
      value <= load_data;
    end
    else if (enable) begin
      value <= value + 1;
    end
  end
endmodule

//ROM - Sí funciona
module ROM_Memory (input wire [11:0]address, output wire [7:0]opcode);
  reg [7:0] ROM [0:4095];
  initial begin
      $readmemh("instructions.list", ROM);
  end
  assign opcode = ROM[address];
endmodule

// Flip Flop Tipo D --> para fetch
module flip_flop8 (input wire clk, reset, enable, input wire [7:0]d, output reg [7:0]q);
	always @ (posedge clk or posedge reset or enable)begin
		if (reset) begin
			q <= 8'b0;
		end
    else if (enable) begin
      q <= d;
    end
	end
endmodule

//Fetch - Sí funciona
module Fetch (input wire clk, reset, enable, input wire [7:0]opcode, output wire [3:0]instruction, operand);
  wire [7:0]q;
  assign instruction = q[7:4];
  assign operand = q[3:0];
  flip_flop8 F1(clk, reset, enable, opcode, q);
endmodule

// Flip Flop Tipo D --> para flags - Sí funciona
module Flags (input wire clk, reset, enable, input wire [1:0]d, output reg [1:0]q);
	always @ (posedge clk or posedge reset or enable)begin
		if (reset) begin
			q <= 2'b0;
		end
    else if (enable) begin
      q <= d;
    end
	end
endmodule

// Flip Flop Tipo D --> para toggle del phase
module flip_flop1 (input wire clk, reset, enable, input wire d, output reg q);
	always @ (posedge clk or posedge reset or enable)begin
		if (reset) begin
			q <= 1'b0;
		end
    else if (enable) begin
      q <= d;
    end
	end
endmodule

// Flip Flop Toggle --> para phase - Sí funciona
module Phase (input wire clk, reset, enable, output wire q);
  wire d;
  assign d = ~q;
	flip_flop1 F1(clk, reset, enable, d, q);
endmodule

//Decode
module Microcode(input wire [6:0]address, output reg [12:0]control);
  always @ (address) begin
    casex (address)
    7'bxxxxxx0: //0
      control <= 13'b1000000001000;
    7'b00001x1: //1
      control <= 13'b0100000001000;
    7'b00000x1: //2
      control <= 13'b1000000001000;
    7'b00011x1: //3
      control <= 13'b1000000001000;
    7'b00010x1: //4
      control <= 13'b0100000001000;
    7'b0010xx1: //5
      control <= 13'b0001001000010;
    7'b0011xx1: //6
      control <= 13'b1001001100000;
    7'b0100xx1: //7
      control <= 13'b0011010000010;
    7'b0101xx1: //8
      control <= 13'b0011010000100;
    7'b0110xx1: //9
      control <= 13'b1011010100000;
    7'b0111xx1: //10
      control <= 13'b1000000111000;
    7'b1000x11: //11
      control <= 13'b0100000001000;
    7'b1000x01: //12
      control <= 13'b1000000001000;
    7'b1001x11: //13
      control <= 13'b1000000001000;
    7'b1001x01: //14
      control <= 13'b0100000001000;
    7'b1010xx1: //15
      control <= 13'b0011011000010;
    7'b1011xx1: //16
      control <= 13'b1011011100000;
    7'b1100xx1: //17
      control <= 13'b0100000001000;
    7'b1101xx1: //18
      control <= 13'b0000000001001;
    7'b1110xx1: //19
      control <= 13'b0011100000010;
    7'b1111xx1: //20
      control <= 13'b1011100100000;
    default:
      control <= 13'b1111111111111;
    endcase
  end
endmodule

// Buffer Tri-estado - Sí funciona
module Tris (input wire enable, input wire [3:0]in, output wire [3:0]out);
  assign out = enable ? in:4'bz;
endmodule

//RAM
module RAM_Memory (input wire enable, write, read, input wire [11:0]address_RAM, inout [3:0]data);
  reg [3:0] RAM [0:4095];
  reg [3:0]data_out;

  //Coloca un tris para poder escribir o leer
  assign data = (enable & read & ~write) ? data_out:4'bz;
  //Bloque de escritura
  always @ ( address_RAM or data or enable or write ) begin
    if (enable && write) begin
      RAM[address_RAM] = data;
    end
  end
  //Bloque de lectura
  always @ ( address_RAM or enable or write or read) begin
    if (enable && ~write && read) begin
      data_out = RAM[address_RAM];
    end
  end
endmodule

// Flip Flop Tipo D - Sí funciona
module Accumulator (input wire clk, reset, enable, input wire [3:0]result, output reg [3:0]accu);
	always @ (posedge clk or posedge reset or enable) begin
		if (reset) begin
			accu <= 4'b0;
		end
    else if (enable) begin
      accu <= result;
    end
	end
endmodule

//ALU - Los 3 bits de seleccion vienen del microcode el databus es el operand y la accu es W
module ALU (input wire [3:0]data_bus, accu, input wire [2:0]selector, output reg [3:0]result, output wire [1:0]flags);
  wire zero;
  reg carry;
  always @ ( * ) begin
    case (selector)
    0:
      {carry, result} <= accu;
    1:
      {carry, result} <= accu - data_bus;
    2:
      {carry, result} <= data_bus;
    3:
      {carry, result} <= accu + data_bus;
    4:
      {carry, result} <= accu ~& data_bus;
    default:
      {carry, result} <= 5'b0;
    endcase
  end
  assign zero = ((result == 4'b0) && (carry == 1'b0)) ? 1'b1:1'b0;
  assign flags[0] = zero;
  assign flags[1] = carry;
endmodule

// Flip Flop Tipo D --> para outputs
module Outputs (input wire clk, reset, enable, input wire [3:0]d, output reg [3:0]q);
	always @ (posedge clk or posedge reset or enable)begin
		if (reset) begin
			q <= 4'b0;
		end
    else if (enable) begin
      q <= d;
    end
	end
endmodule

//Nibbler
module uP (input wire clock, reset, input wire [3:0]pushbuttons, output wire phase, c_flag, z_flag, output wire [3:0]instr, oprnd, data_bus, FF_out, accu, output wire [7:0]program_byte, output wire [11:0]PC, address_RAM);
  //Cables internos del Nibbler
  wire [1:0]flags_in, flags_out; //posicion 1 es carry y 0 es zero
  wire [12:0]control;
  wire [3:0]alu_result;
  wire [6:0]address;
  //Defino a address como la contatenacion de varias entradas
  assign address = {instr, c_flag, z_flag, phase};
  //address_RAM
  assign address_RAM = {oprnd, program_byte};
  //Defino mis banderas concatenadas
  assign c_flag = flags_out[1];
  assign z_flag = flags_out[0];
  //Defino a los bits de control con mi address a traves del decode
  Microcode M1(address, control);
  //Doy valor al PC a traves de las señales de control 11 y 12 -load y enable respectivamente-
  Counter PC1(clock, reset, control[11], control[12], address_RAM, PC);
  //Busco la instruccion correspondiente en la ROM con el PC
  ROM_Memory ROM1(PC, program_byte);
  //Fetch divide al program_byte -opcode- en instruccion y operando
  Fetch FE1(clock, reset, ~phase, program_byte, instr, oprnd);
  //Uso el toggle para definir el phase
  Phase PH1(clock, reset, 1'b1, phase); //Enable del phase siempre en 1?????
  //Dejo pasar mis banderas con el bit 9 de control -LoadFlags-
  Flags FL1(clock, reset, control[9], flags_in, flags_out);
  //Primer Bus Driver - Defino a data_bus usando el bit 1 de control -oeOprnd-
  Tris BD1(control[1], oprnd, data_bus);
  //Operaciones con ALU entra data_bus y accu, selecciono con los bits 6, 7 y 8 de control, sale el resultado y las banderas
  ALU A1(data_bus, accu, control[8:6], alu_result, flags_in);
  //Genero el registro W - Defino a accu a traves del resultado de la ALU y del bit 10 de control -loadA-
  Accumulator A2(clock, reset, control[10], alu_result, accu);
  //Segundo Bus Driver - Defino a data_bus usando el bit 3 de control -oeALU-
  Tris BD2(control[3], alu_result, data_bus);
  //Definicion de la RAM uso de control 4 y 5 -weRAM y csRAM respectivamente-
  RAM_Memory RAM1(control[5], control[4], control[5], address_RAM, data_bus); //output enable de la RAM es cuando los otros tres tris estan en cero????
  //Tercer Bus Driver - Defino a data_bus usando el bit 2 de control -oeIN-
  Tris BD3(control[2], pushbuttons, data_bus);
  //Flip flop para Outputs con bit 0 de control -loadOut-
  Outputs O1(clock, reset, control[0], data_bus, FF_out);
endmodule

Nibbler/Prueba/uP_tb.v

module testbench();

  reg clock, reset;
  reg [3:0] pushbuttons;
  wire phase, c_flag, z_flag;
  wire [3:0] instr, oprnd, accu, data_bus, FF_out;
  wire [7:0] program_byte;
  wire [11:0] PC, address_RAM;

  integer nota = 0;
  integer immediateDelay = 16;
  integer jumpDelay = 276;
  integer memoryDelay = 0;

  uP uPmodule(.clock(clock),
              .reset(reset),
              .pushbuttons(pushbuttons),
              .phase(phase),
              .c_flag(c_flag),
              .z_flag(z_flag),
              .instr(instr),
              .oprnd(oprnd),
              .accu(accu),
              .data_bus(data_bus),
              .FF_out(FF_out),
              .program_byte(program_byte),
              .PC(PC),
              .address_RAM(address_RAM));

  initial
      #750 $finish;

  always
      #5 clock = ~clock;

  initial begin
      clock = 0; reset = 0; pushbuttons = 4'b0110; nota = 0;
      #2 reset = 1;
      #1 reset = 0;
      $display("\n");
      $display("Bienvenido al testbench de su proyecto");
      $display("\n");
      $display("Para facilitar el codigo del testbench la nota se ha");
      $display("multplicado por 10. Es decir, la nota maxima de esta");
      $display("prueba es de 900. Obviamente su nota en Canvas no sera de");
      $display("ese valor sino que se dividira dentro de 10.");
      $display("Es decir, su nota es sobre 9.0 puntos netos.");
      $display("\n");
  end

  initial begin
      $dumpfile("uP_tb.vcd");
      $dumpvars(0, testbench);
  end

  initial begin
      #immediateDelay
      if (PC === 12'h001 && accu === 4'hF) begin
          nota = nota + 70;
          $display("LIT funciona bien. Su nota es: %d/900\n", nota);
      end
      else
          $display("LIT NO funciona bien. Su nota es: %d/900\n", nota);
  end

  initial begin
      #(immediateDelay+20*1)
      if (PC === 12'h002 && accu === 4'hF && FF_out === 4'hF) begin
          nota = nota + 33;
          $display("OUT parece funcionar bien. Su nota es: %d/900\n", nota);
      end
      else
          $display("OUT NO funciona bien. Su nota es: %d/900\n", nota);
  end

  initial begin
      #(immediateDelay + 20 * 2)
      if (PC === 12'h003 && accu === 4'h6) begin
          nota = nota + 33;
          $display("IN parece funcionar bien. Su nota es: %d/900\n", nota);
      end
      else
          $display("IN NO funciona bien. Su nota es: %d/900\n", nota);
  end

  initial begin
      #(immediateDelay + 20 * 3)
      if (PC === 12'h004 && accu === 4'h0 && z_flag === 1'b1) begin
          $display("La bandera zero se encendio al colocar 4'b0000 en la salida de la ALU.\n");
      end
      else
          $display("La bandera zero NO se encendio al colocar 4'b0000 en la salida de la ALU.\n", nota);
  end

  initial begin
      #(immediateDelay + 20 * 5)
      if (PC === 12'h006 && accu === 4'h9 && c_flag === 1'b1) begin
          nota = nota + 33;
          $display("ADDI y la bandera carry funcionan bien. Su nota es: %d/900\n", nota);
      end
      else
          $display("ADDI y/o la bandera carry NO funcionan bien. Su nota es: %d/900\n", nota);
  end

  initial begin
      #(immediateDelay + 20 * 6)
      if (PC === 12'h007 && accu === 4'h9 && c_flag === 1'b0) begin
          nota = nota + 33;
          $display("CMPI de A > B hace que la bandera carry este en 0 (como deberia estar). Su nota es %d/900\n", nota);
      end
      else
          $display("CMPI de A > B causa que la bandera carry esté en 1 o modifico el valor del Accu. Su nota es %d/900\n", nota);
  end

  initial begin
      #(immediateDelay + 20 * 8)
      if (PC === 12'h009 && accu === 4'hA && c_flag === 1'b1) begin
          nota = nota + 33;
          $display("CMPI de A < B hace que la bandera carry este en 1 (como deberia estar). Su nota es %d/900\n", nota);
      end
      else
          $display("CMPI de A > B causa que la bandera carry este en 1 o modifico el valor del Accu.  Su nota es %d/900\n", nota);
  end

  initial begin
      #(immediateDelay + 20 * 9)
      if (PC === 12'h00A && accu === 4'hB && c_flag === 1'b0 && z_flag === 1'b0) begin
          nota = nota + 33;
          $display("ADDI sin overflow no levanta las banderas (como deberia estar). Su nota es %d/900\n", nota);
      end
      else
          $display("ADDI sin overflow levanto alguna de las banderas o no realizo bien la suma.  Su nota es %d/900\n", nota);
  end

  initial begin
      #(immediateDelay + 20 * 10)
      if (PC === 12'h00B && accu === 4'h4 && c_flag === 1'b0 && z_flag === 1'b0) begin
          nota = nota + 66;
          $display("NANDI funciona bien. Su nota es %d/900\n", nota);
      end
      else
          $display("NANDI NO funciona bien.  Su nota es %d/900\n", nota);
  end

  initial begin
      #(immediateDelay + 20 * 11)
      if (PC === 12'h00C && accu === 4'h4 && c_flag === 1'b0 && z_flag === 1'b0 && FF_out === 4'h4) begin
          nota = nota + 33;
          $display("OUT funciona bien (la verificacion de OUT se hizo en 2 partes). Su nota es %d/900\n", nota);
      end
      else
          $display("OUT NO funciona bien (la verificacion de OUT se hizo en 2 partes).  Su nota es %d/900\n", nota);
      pushbuttons = 4'hE;
  end

  initial begin
      #(immediateDelay + 20 * 12)
      if (PC === 12'h00D && accu === 4'hE && c_flag === 1'b0 && z_flag === 1'b0 && FF_out === 4'h4) begin
          nota = nota + 33;
          $display("IN funciona bien (la verificacion de IN se hizo en 2 partes). Su nota es %d/900\n", nota);
      end
      else
          $display("IN NO funciona bien (la verificacion de IN se hizo en 2 partes).  Su nota es %d/900\n", nota);
      pushbuttons = 4'hE;

      $display("-----------------------------------------------------------------------------------------------------------------------------");
      $display("Hasta este punto se han verificado todas las instrucciones con inmediatos. Ahora se verificaran las instrucciones con saltos.");
      $display("La nota maxima (hasta este punto) es 400.\n");
  end

  initial begin
      #(jumpDelay)//276
      if (PC === 12'hA01) begin
          nota = nota + 60;
          $display("JMP funciona bien. Ahora estamos en PC = 12'hA01. Su nota es %d/900\n", nota);
      end
      else
          $display("JMP NO funciona bien. El PC no esta en la localidad 12'HA01.  Su nota es %d/900\n", nota);
  end

  initial begin
      #(jumpDelay + 20 * 3) //336
      if (PC === 12'h050 && c_flag === 1'b1) begin
          nota = nota + 30;
          $display("JC parece funcionar bien con carry = 1 (1/2). Ahora estamos en PC = 12'h050. Su nota es %d/900\n", nota);
      end
      else
          $display("JC NO funciona bien. El PC no esta en la localidad 12'HA01 o carry no es 1.  Su nota es %d/900\n", nota);
  end

  initial begin
      #(jumpDelay + 20 * 6)//396
      if (PC === 12'hF49 && z_flag === 1'b1) begin
          nota = nota + 30;
          $display("JZ parece funcionar bien con zero = 1 (1/2). Ahora estamos en PC = 12'hF49. Su nota es %d/900\n", nota);
      end
      else
          $display("JZ NO funciona bien. El PC no está en la localidad 12'hA01 ó zero no es 1.  Su nota es %d/900\n", nota);
  end

  initial begin
      #(jumpDelay + 20 * 9)//456
      if (PC === 12'hF4D && z_flag === 1'b0 && c_flag === 1'b0 && accu === 4'h6) begin
          nota = nota + 30;
          $display("JC parece funcionar bien con carry = 0 (2/2). El PC aumento en +1 en vez de saltar. Su nota es %d/900\n", nota);
      end
      else
          $display("JC NO funciona bien. El PC salto a otra localidad o zero = 1 ó carry =1 ó por alguna razón su accu cambió de valor.  Su nota es %d/900\n", nota);
  end

  initial begin
      #(jumpDelay + 20 * 10)//476
      if (PC === 12'hF4F && z_flag === 1'b0 && c_flag === 1'b0 && accu === 4'h6) begin
          nota = nota + 30;
          $display("JZ parece funcionar bien con zero = 0 (2/2). El PC aumento en +1 en vez de saltar. Su nota es %d/900\n", nota);
      end
      else
          $display("JZ NO funciona bien. El PC salto a otra localidad ó zero = 1 ó carry =1 o por alguna razon su accu cambió de valor.  Su nota es %d/900\n", nota);
  end

  initial begin
      #(jumpDelay + 20 * 11)//496
      if (PC === 12'h223 && z_flag === 1'b0 && c_flag === 1'b0 && accu === 4'h6) begin
          nota = nota + 30;
          $display("JNC parece funcionar bien con carry = 0 (1/2). El PC = 12'h223, c_flag = 0, z_flag = 0, accu = 4'h6. Su nota es %d/900\n", nota);
      end
      else
          $display("JNC NO funciona bien (2/2). El PC no esta en 12'h223, alguna bandera esta encendida o el accu cambio por alguna razon. Su nota es %d/900\n", nota);
  end

endmodule

Nibbler/Prueba/uP_tb.vcd
$date
	Wed Nov 18 22:12:13 2020
$end
$version
	Icarus Verilog
$end
$timescale
	1ps
$end
$scope module testbench $end
$var wire 4 ! data_bus [3:0] $end
$var wire 1 " z_flag $end
$var wire 8 # program_byte [7:0] $end
$var wire 1 $ phase $end
$var wire 4 % oprnd [3:0] $end
$var wire 4 & instr [3:0] $end
$var wire 1 ' c_flag $end
$var wire 12 ( address_RAM [11:0] $end
$var wire 4 ) accu [3:0] $end
$var wire 12 * PC [11:0] $end
$var wire 4 + FF_out [3:0] $end
$var reg 1 , clock $end
$var reg 4 - pushbuttons [3:0] $end
$var reg 1 . reset $end
$var integer 32 / immediateDelay [31:0] $end
$var integer 32 0 jumpDelay [31:0] $end
$var integer 32 1 memoryDelay [31:0] $end
$var integer 32 2 nota [31:0] $end
$scope module uPmodule $end
$var wire 1 , clock $end
$var wire 4 3 data_bus [3:0] $end
$var wire 4 4 pushbuttons [3:0] $end
$var wire 1 . reset $end
$var wire 1 " z_flag $end
$var wire 8 5 program_byte [7:0] $end
$var wire 1 $ phase $end
$var wire 4 6 oprnd [3:0] $end
$var wire 4 7 instr [3:0] $end
$var wire 2 8 flags_out [1:0] $end
$var wire 2 9 flags_in [1:0] $end
$var wire 13 : control [12:0] $end
$var wire 1 ' c_flag $end
$var wire 4 ; alu_result [3:0] $end
$var wire 12 < address_RAM [11:0] $end
$var wire 7 = address [6:0] $end
$var wire 4 > accu [3:0] $end
$var wire 12 ? PC [11:0] $end
$var wire 4 @ FF_out [3:0] $end
$scope module A1 $end
$var wire 4 A data_bus [3:0] $end
$var wire 3 B selector [2:0] $end
$var wire 1 C zero $end
$var wire 2 D flags [1:0] $end
$var wire 4 E accu [3:0] $end
$var reg 1 F carry $end
$var reg 4 G result [3:0] $end
$upscope $end
$scope module A2 $end
$var wire 1 , clk $end
$var wire 1 H enable $end
$var wire 1 . reset $end
$var wire 4 I result [3:0] $end
$var reg 4 J accu [3:0] $end
$upscope $end
$scope module BD1 $end
$var wire 1 K enable $end
$var wire 4 L out [3:0] $end
$var wire 4 M in [3:0] $end
$upscope $end
$scope module BD2 $end
$var wire 1 N enable $end
$var wire 4 O in [3:0] $end
$var wire 4 P out [3:0] $end
$upscope $end
$scope module BD3 $end
$var wire 1 Q enable $end
$var wire 4 R in [3:0] $end
$var wire 4 S out [3:0] $end
$upscope $end
$scope module FE1 $end
$var wire 1 , clk $end
$var wire 1 T enable $end
$var wire 1 . reset $end
$var wire 8 U q [7:0] $end
$var wire 4 V operand [3:0] $end
$var wire 8 W opcode [7:0] $end
$var wire 4 X instruction [3:0] $end
$scope module F1 $end
$var wire 1 , clk $end
$var wire 1 T enable $end
$var wire 1 . reset $end
$var wire 8 Y d [7:0] $end
$var reg 8 Z q [7:0] $end
$upscope $end
$upscope $end
$scope module FL1 $end
$var wire 1 , clk $end
$var wire 2 [ d [1:0] $end
$var wire 1 \ enable $end
$var wire 1 . reset $end
$var reg 2 ] q [1:0] $end
$upscope $end
$scope module M1 $end
$var wire 7 ^ address [6:0] $end
$var reg 13 _ control [12:0] $end
$upscope $end
$scope module O1 $end
$var wire 1 , clk $end
$var wire 4 ` d [3:0] $end
$var wire 1 a enable $end
$var wire 1 . reset $end
$var reg 4 b q [3:0] $end
$upscope $end
$scope module PC1 $end
$var wire 1 , clock $end
$var wire 1 c enable $end
$var wire 1 d load $end
$var wire 12 e load_data [11:0] $end
$var wire 1 . reset $end
$var reg 12 f value [11:0] $end
$upscope $end
$scope module PH1 $end
$var wire 1 , clk $end
$var wire 1 g d $end
$var wire 1 h enable $end
$var wire 1 . reset $end
$var wire 1 $ q $end
$scope module F1 $end
$var wire 1 , clk $end
$var wire 1 g d $end
$var wire 1 h enable $end
$var wire 1 . reset $end
$var reg 1 $ q $end
$upscope $end
$upscope $end
$scope module RAM1 $end
$var wire 12 i address_RAM [11:0] $end
$var wire 4 j data [3:0] $end
$var wire 1 k enable $end
$var wire 1 l read $end
$var wire 1 m write $end
$var reg 4 n data_out [3:0] $end
$upscope $end
$scope module ROM1 $end
$var wire 12 o address [11:0] $end
$var wire 8 p opcode [7:0] $end
$upscope $end
$upscope $end
$upscope $end
$enddefinitions $end
#0
$dumpvars
bx p
bx o
bx n
xm
xl
xk
bx j
bx i
1h
xg
bx f
bx e
xd
xc
bx b
xa
bx `
bx _
bx ^
bx ]
x\
bx [
bx Z
bx Y
bx X
bx W
bx V
bx U
xT
bx S
b110 R
xQ
bx P
bx O
xN
bx M
bx L
xK
bx J
bx I
xH
bx G
xF
bx E
bx D
xC
bx B
bx A
bx @
bx ?
bx >
bx =
bx <
bx ;
bx :
bx 9
bx 8
bx 7
bx 6
bx 5
b110 4
bx 3
b0 2
b0 1
b100010100 0
b10000 /
0.
b110 -
0,
bx +
bx *
bx )
bx (
x'
bx &
bx %
x$
bx #
x"
bx !
$end
#2
b0 !
b0 3
b0 A
b0 L
b0 P
b0 S
b0 `
b0 j
1C
0a
0Q
0l
0m
0k
1N
0H
b0 B
0K
0\
1c
0d
b1 9
b1 D
b1 [
0F
b0 ;
b0 G
b0 I
b0 O
b1000000001000 :
b1000000001000 _
b0 %
b0 6
b0 M
b0 V
b0 &
b0 7
b0 X
0"
0'
1g
1T
b0 )
b0 >
b0 E
b0 J
b0 U
b0 Z
b0 8
b0 ]
b0 +
b0 @
b0 b
b1001111 (
b1001111 <
b1001111 e
b1001111 i
b1001111 #
b1001111 5
b1001111 W
b1001111 Y
b1001111 p
b0 *
b0 ?
b0 f
b0 o
b0 =
b0 ^
0$
1.
#3
0.
#5
b0 9
b0 D
b0 [
0C
1"
b1111 ;
b1111 G
b1111 I
b1111 O
b1 8
b1 ]
b1111 !
b1111 3
b1111 A
b1111 L
b1111 P
b1111 S
b1111 `
b1111 j
0N
1H
b10 B
1K
1\
0c
b11010000010 :
b11010000010 _
b1111 %
b1111 6
b1111 M
b1111 V
b100 &
b100 7
b100 X
0g
0T
b1001111 U
b1001111 Z
b111111011111 (
b111111011111 <
b111111011111 e
b111111011111 i
b11011111 #
b11011111 5
b11011111 W
b11011111 Y
b11011111 p
b1 *
b1 ?
b1 f
b1 o
b100011 =
b100011 ^
1$
1,
#10
0,
#15
b1111 !
b1111 3
b1111 A
b1111 L
b1111 P
b1111 S
b1111 `
b1111 j
b1101 &
b1101 7
b1101 X
1N
0H
b0 B
0K
0\
1c
b11011111 U
b11011111 Z
b1000000001000 :
b1000000001000 _
0"
1g
1T
b1111 )
b1111 >
b1111 E
b1111 J
b0 8
b0 ]
b1101000 =
b1101000 ^
0$
1,
#16
b1000110 2
#20
0,
#25
b1111 +
b1111 @
b1111 b
1a
0c
b1001 :
b1001 _
0g
0T
b111101010001 (
b111101010001 <
b111101010001 e
b111101010001 i
b1010001 #
b1010001 5
b1010001 W
b1010001 Y
b1010001 p
b10 *
b10 ?
b10 f
b10 o
b1101001 =
b1101001 ^
1$
1,
#30
0,
#35
b101010001 (
b101010001 <
b101010001 e
b101010001 i
b1 %
b1 6
b1 M
b1 V
b101 &
b101 7
b101 X
0a
1c
b1010001 U
b1010001 Z
b1000000001000 :
b1000000001000 _
1g
1T
b101000 =
b101000 ^
0$
1,
#36
b1100111 2
#40
0,
#45
b110 ;
b110 G
b110 I
b110 O
b110 !
b110 3
b110 A
b110 L
b110 P
b110 S
b110 `
b110 j
1Q
0N
1H
b10 B
1\
0c
b11010000100 :
b11010000100 _
0g
0T
b101000000 (
b101000000 <
b101000000 e
b101000000 i
b1000000 #
b1000000 5
b1000000 W
b1000000 Y
b1000000 p
b11 *
b11 ?
b11 f
b11 o
b101001 =
b101001 ^
1$
1,
#50
0,
#55
b1000000 (
b1000000 <
b1000000 e
b1000000 i
b0 %
b0 6
b0 M
b0 V
b100 &
b100 7
b100 X
0Q
1N
0H
b0 B
0\
1c
b1000000 U
b1000000 Z
b1000000001000 :
b1000000001000 _
1g
1T
b110 )
b110 >
b110 E
b110 J
b100000 =
b100000 ^
0$
1,
#56
b10001000 2
#60
0,
#65
b1 9
b1 D
b1 [
1C
b0 ;
b0 G
b0 I
b0 O
b0 !
b0 3
b0 A
b0 L
b0 P
b0 S
b0 `
b0 j
0N
1H
b10 B
1K
1\
0c
b11010000010 :
b11010000010 _
0g
0T
b1001111 (
b1001111 <
b1001111 e
b1001111 i
b1001111 #
b1001111 5
b1001111 W
b1001111 Y
b1001111 p
b100 *
b100 ?
b100 f
b100 o
b100001 =
b100001 ^
1$
1,
#70
0,
#75
b0 !
b0 3
b0 A
b0 L
b0 P
b0 S
b0 `
b0 j
b111101001111 (
b111101001111 <
b111101001111 e
b111101001111 i
b1111 %
b1111 6
b1111 M
b1111 V
1N
0H
b0 B
0K
0\
1c
b1001111 U
b1001111 Z
b1000000001000 :
b1000000001000 _
1"
1g
1T
b0 )
b0 >
b0 E
b0 J
b1 8
b1 ]
b100010 =
b100010 ^
0$
1,
#80
0,
#85
b0 9
b0 D
b0 [
0C
b1111 ;
b1111 G
b1111 I
b1111 O
b1111 !
b1111 3
b1111 A
b1111 L
b1111 P
b1111 S
b1111 `
b1111 j
0N
1H
b10 B
1K
1\
0c
b11010000010 :
b11010000010 _
0g
0T
b111110101010 (
b111110101010 <
b111110101010 e
b111110101010 i
b10101010 #
b10101010 5
b10101010 W
b10101010 Y
b10101010 p
b101 *
b101 ?
b101 f
b101 o
b100011 =
b100011 ^
1$
1,
#90
0,
#95
b1111 !
b1111 3
b1111 A
b1111 L
b1111 P
b1111 S
b1111 `
b1111 j
b101010101010 (
b101010101010 <
b101010101010 e
b101010101010 i
b1010 %
b1010 6
b1010 M
b1010 V
b1010 &
b1010 7
b1010 X
1N
0H
b0 B
0K
0\
1c
b10101010 U
b10101010 Z
b1000000001000 :
b1000000001000 _
0"
1g
1T
b1111 )
b1111 >
b1111 E
b1111 J
b0 8
b0 ]
b1010000 =
b1010000 ^
0$
1,
#100
0,
#105
b10 9
b10 D
b10 [
1F
b1001 ;
b1001 G
b1001 I
b1001 O
b1010 !
b1010 3
b1010 A
b1010 L
b1010 P
b1010 S
b1010 `
b1010 j
0N
1H
b11 B
1K
1\
0c
b11011000010 :
b11011000010 _
0g
0T
b101000101000 (
b101000101000 <
b101000101000 e
b101000101000 i
b101000 #
b101000 5
b101000 W
b101000 Y
b101000 p
b110 *
b110 ?
b110 f
b110 o
b1010001 =
b1010001 ^
1$
1,
#110
0,
#115
b0 9
b0 D
b0 [
0F
b1001 !
b1001 3
b1001 A
b1001 L
b1001 P
b1001 S
b1001 `
b1001 j
b100000101000 (
b100000101000 <
b100000101000 e
b100000101000 i
b1000 %
b1000 6
b1000 M
b1000 V
b10 &
b10 7
b10 X
1N
0H
b0 B
0K
0\
1c
b101000 U
b101000 Z
b1001 ;
b1001 G
b1001 I
b1001 O
b1000000001000 :
b1000000001000 _
1'
1g
1T
b1001 )
b1001 >
b1001 E
b1001 J
b10 8
b10 ]
b10100 =
b10100 ^
0$
1,
#116
b10101001 2
#120
0,
#125
0'
b0 9
b0 D
b0 [
0F
b1 ;
b1 G
b1 I
b1 O
b0 8
b0 ]
b1000 !
b1000 3
b1000 A
b1000 L
b1000 P
b1000 S
b1000 `
b1000 j
0N
b1 B
1K
1\
0c
b1001000010 :
b1001000010 _
0g
0T
b100001001010 (
b100001001010 <
b100001001010 e
b100001001010 i
b1001010 #
b1001010 5
b1001010 W
b1001010 Y
b1001010 p
b111 *
b111 ?
b111 f
b111 o
b10001 =
b10001 ^
1$
1,
#130
0,
#135
b1001 ;
b1001 G
b1001 I
b1001 O
b1001 !
b1001 3
b1001 A
b1001 L
b1001 P
b1001 S
b1001 `
b1001 j
b101001001010 (
b101001001010 <
b101001001010 e
b101001001010 i
b1010 %
b1010 6
b1010 M
b1010 V
b100 &
b100 7
b100 X
1N
b0 B
0K
0\
1c
b1001010 U
b1001010 Z
b1000000001000 :
b1000000001000 _
1g
1T
b100000 =
b100000 ^
0$
1,
#136
b11001010 2
#140
0,
#145
b1010 ;
b1010 G
b1010 I
b1010 O
b1010 !
b1010 3
b1010 A
b1010 L
b1010 P
b1010 S
b1010 `
b1010 j
0N
1H
b10 B
1K
1\
0c
b11010000010 :
b11010000010 _
0g
0T
b101000101100 (
b101000101100 <
b101000101100 e
b101000101100 i
b101100 #
b101100 5
b101100 W
b101100 Y
b101100 p
b1000 *
b1000 ?
b1000 f
b1000 o
b100001 =
b100001 ^
1$
1,
#150
0,
#155
b1010 !
b1010 3
b1010 A
b1010 L
b1010 P
b1010 S
b1010 `
b1010 j
b110000101100 (
b110000101100 <
b110000101100 e
b110000101100 i
b1100 %
b1100 6
b1100 M
b1100 V
b10 &
b10 7
b10 X
1N
0H
b0 B
0K
0\
1c
b101100 U
b101100 Z
b1000000001000 :
b1000000001000 _
1g
1T
b1010 )
b1010 >
b1010 E
b1010 J
b10000 =
b10000 ^
0$
1,
#160
0,
#165
b10 9
b10 D
b10 [
1F
b1110 ;
b1110 G
b1110 I
b1110 O
b1100 !
b1100 3
b1100 A
b1100 L
b1100 P
b1100 S
b1100 `
b1100 j
0N
b1 B
1K
1\
0c
b1001000010 :
b1001000010 _
0g
0T
b110010100001 (
b110010100001 <
b110010100001 e
b110010100001 i
b10100001 #
b10100001 5
b10100001 W
b10100001 Y
b10100001 p
b1001 *
b1001 ?
b1001 f
b1001 o
b10001 =
b10001 ^
1$
1,
#170
0,
#175
b0 9
b0 D
b0 [
0F
b1010 ;
b1010 G
b1010 I
b1010 O
b1010 !
b1010 3
b1010 A
b1010 L
b1010 P
b1010 S
b1010 `
b1010 j
b110100001 (
b110100001 <
b110100001 e
b110100001 i
b1 %
b1 6
b1 M
b1 V
b1010 &
b1010 7
b1010 X
1N
b0 B
0K
0\
1c
b10100001 U
b10100001 Z
b1000000001000 :
b1000000001000 _
1'
1g
1T
b10 8
b10 ]
b1010100 =
b1010100 ^
0$
1,
#176
b11101011 2
#180
0,
#185
0'
b0 9
b0 D
b0 [
0F
b1011 ;
b1011 G
b1011 I
b1011 O
b0 8
b0 ]
b1 !
b1 3
b1 A
b1 L
b1 P
b1 S
b1 `
b1 j
0N
1H
b11 B
1K
1\
0c
b11011000010 :
b11011000010 _
0g
0T
b111101011 (
b111101011 <
b111101011 e
b111101011 i
b11101011 #
b11101011 5
b11101011 W
b11101011 Y
b11101011 p
b1010 *
b1010 ?
b1010 f
b1010 o
b1010001 =
b1010001 ^
1$
1,
#190
0,
