Lab9/Codigo/Ejercicio1/code.v
//-----------------------------------
// Ricardo Pellecer Orellana
// Carné: 19072
// 30/Octubre/2020
// -----------------------------------

// Ejercicio 1
// Flip Flop Tipo D
module flip_flop_1(input wire clk, reset, enable,
				 input wire d,
				 output reg q);
	always @ (posedge clk or posedge reset or enable)begin
		if (reset) begin
			q <= 1'b0;
		end
    else if (enable) begin
      q <= d;
    end
	end
endmodule

module flip_flop_2(input wire clk, reset, enable,
				 input wire [1:0]d,
				 output wire [1:0]q);
  flip_flop_1 F1(clk, reset, enable, d[0], q[0]);
  flip_flop_1 F2(clk, reset, enable, d[1], q[1]);
endmodule

module flip_flop_4(input wire clk, reset, enable,
				 input wire [3:0]d,
				 output wire [3:0]q);
  flip_flop_1 F1(clk, reset, enable, d[0], q[0]);
  flip_flop_1 F2(clk, reset, enable, d[1], q[1]);
  flip_flop_1 F3(clk, reset, enable, d[2], q[2]);
  flip_flop_1 F4(clk, reset, enable, d[3], q[3]);
endmodule

Lab9/Codigo/Ejercicio1/code_tb.v
module testbench();
  //Variables de entrada
  reg clock, enable, reset, d1;
  reg [1:0]d2; //flip flop 2 bit
  reg [3:0]d4; //flip flop 4 bit

  //Variables de salida
  wire q1;
  wire [1:0]q2; //flip flop 2 bit
  wire [3:0]q4; //flip flop 4 bit

  //Instanciaciones
  flip_flop_1 F1(clock, reset, enable, d1, q1);
  flip_flop_2 F2(clock, reset, enable, d2, q2);
  flip_flop_4 F3(clock, reset, enable, d4, q4);

  always
    #1 clock <=~clock;

    //Ejercicio 1
    initial begin
    #2
    $display(" \nFlip Flops Tipo D ");
    $display(" \nUn Bit ");
    $display("clock reset enable    D   |   Q ");
    $display("--------------------------|--------");
    $monitor("%b       %b     %b       %b   |   %b", clock, reset, enable, d1, q1);

      enable = 0; reset = 0; d1 = 0; clock = 0; d2 = 2'b0; d4 = 4'b0;
  #2  enable = 0; reset = 1; d1 = 0;
  #2  enable = 1; reset = 0; d1 = 0;
  #2  enable = 1; reset = 0; d1 = 1;
  #2  enable = 1; reset = 0; d1 = 0;
  #2
    $display(" \nDos Bits ");
    $display("clock reset enable  D  |   Q ");
    $display("-----------------------|--------");
    $monitor("%b       %b      %b    %b |   %b", clock, reset, enable, d2, q2);

      enable = 0; reset = 0; d2 = 2'b0;
  #2  enable = 1; reset = 0; d2 = 2'b10;
  #2  enable = 1; reset = 0; d2 = 2'b01;
  #2  enable = 1; reset = 0; d2 = 2'b11;
  #2
    $display(" \nCuatro Bits ");
    $display("clock reset enable     D  |   Q ");
    $display("--------------------------|--------");
    $monitor("%b       %b      %b     %b |  %b", clock, reset, enable, d4, q4);

      enable = 0; reset = 0; d4 = 4'b0;
  #2  enable = 1; reset = 0; d4 = 4'b1000;
  #2  enable = 1; reset = 0; d4 = 4'b0101;
  #2  enable = 1; reset = 0; d4 = 4'b1100;
    end

    initial
      #28 $finish;
    initial begin
        $dumpfile("code_tb.vcd");
        $dumpvars(0, testbench);
      end
  endmodule

Lab9/Codigo/Ejercicio1/code_tb.vcd
$date
	Sat Oct 31 00:57:14 2020
$end
$version
	Icarus Verilog
$end
$timescale
	1ps
$end
$scope module testbench $end
$var wire 4 ! q4 [3:0] $end
$var wire 2 " q2 [1:0] $end
$var wire 1 # q1 $end
$var reg 1 $ clock $end
$var reg 1 % d1 $end
$var reg 2 & d2 [1:0] $end
$var reg 4 ' d4 [3:0] $end
$var reg 1 ( enable $end
$var reg 1 ) reset $end
$scope module F1 $end
$var wire 1 $ clk $end
$var wire 1 % d $end
$var wire 1 ( enable $end
$var wire 1 ) reset $end
$var reg 1 # q $end
$upscope $end
$scope module F2 $end
$var wire 1 $ clk $end
$var wire 2 * d [1:0] $end
$var wire 1 ( enable $end
$var wire 1 ) reset $end
$var wire 2 + q [1:0] $end
$scope module F1 $end
$var wire 1 $ clk $end
$var wire 1 , d $end
$var wire 1 ( enable $end
$var wire 1 ) reset $end
$var reg 1 - q $end
$upscope $end
$scope module F2 $end
$var wire 1 $ clk $end
$var wire 1 . d $end
$var wire 1 ( enable $end
$var wire 1 ) reset $end
$var reg 1 / q $end
$upscope $end
$upscope $end
$scope module F3 $end
$var wire 1 $ clk $end
$var wire 4 0 d [3:0] $end
$var wire 1 ( enable $end
$var wire 1 ) reset $end
$var wire 4 1 q [3:0] $end
$scope module F1 $end
$var wire 1 $ clk $end
$var wire 1 2 d $end
$var wire 1 ( enable $end
$var wire 1 ) reset $end
$var reg 1 3 q $end
$upscope $end
$scope module F2 $end
$var wire 1 $ clk $end
$var wire 1 4 d $end
$var wire 1 ( enable $end
$var wire 1 ) reset $end
$var reg 1 5 q $end
$upscope $end
$scope module F3 $end
$var wire 1 $ clk $end
$var wire 1 6 d $end
$var wire 1 ( enable $end
$var wire 1 ) reset $end
$var reg 1 7 q $end
$upscope $end
$scope module F4 $end
$var wire 1 $ clk $end
$var wire 1 8 d $end
$var wire 1 ( enable $end
$var wire 1 ) reset $end
$var reg 1 9 q $end
$upscope $end
$upscope $end
$upscope $end
$enddefinitions $end
#0
$dumpvars
x9
x8
x7
x6
x5
x4
x3
x2
bx 1
bx 0
x/
x.
x-
x,
bx +
bx *
x)
x(
bx '
bx &
x%
x$
x#
bx "
bx !
$end
#2
02
04
06
08
0,
0.
b0 '
b0 0
b0 &
b0 *
1$
0%
0)
0(
#3
0$
#4
0#
0-
b0 "
b0 +
0/
03
05
07
b0 !
b0 1
09
1$
1)
#5
0$
#6
1$
0)
1(
#7
0$
#8
1#
1$
1%
#9
0$
#10
0#
1$
0%
#11
0$
#12
1$
0(
#13
0$
#14
b10 "
b10 +
1/
1$
1.
b10 &
b10 *
1(
#15
0$
#16
1-
b1 "
b1 +
0/
1$
1,
0.
b1 &
b1 *
#17
0$
#18
b11 "
b11 +
1/
1$
1.
b11 &
b11 *
#19
0$
#20
1$
0(
#21
0$
#22
b1000 !
b1000 1
19
1$
18
b1000 '
b1000 0
1(
#23
0$
#24
13
17
b101 !
b101 1
09
1$
12
16
08
b101 '
b101 0
#25
0$
#26
19
b1100 !
b1100 1
03
1$
02
18
b1100 '
b1100 0
