Lab10/Codigo/Ejercicio1/Ejercicio1.v
//Counter - Sí funciona
module Counter (input wire clock, reset, load, enable, input wire [11:0]load_data, output reg [11:0]value);
  always @ (posedge clock, posedge reset, load, load_data) begin
    if (reset) begin
      value <= 12'b0;
    end
    else if (load) begin
      value <= load_data;
    end
    else if (enable) begin
      if (value < 12'b111111111111) begin
        value <= value + 1;
      end
    end
  end
endmodule

//ROM - Sí funciona
module ROM_Memory (input wire [11:0]address, output wire [7:0]opcode);
  reg [7:0] ROM [0:4095];
  initial begin
      $readmemh("ejemplo.list", ROM);
  end
  assign opcode = ROM[address];
endmodule

// Flip Flop Tipo D
module flip_flop (input wire clk, reset, enable, input wire [7:0]d, output reg [7:0]q);
	always @ (posedge clk or posedge reset or enable)begin
		if (reset) begin
			q <= 8'b0;
		end
    else if (enable) begin
      q <= d;
    end
	end
endmodule

//Fetch
module Fetch (input wire clk, reset, enable, input wire [7:0]opcode, output wire [3:0]instruction, operand);
  wire [7:0]q;
  assign instruction = q[7:4];
  assign operand = q[3:0];
  flip_flop F1(clk, reset, enable, opcode, q);
endmodule

//Union de Modulos
module Program (input wire clk, reset, enablec, enablef, load, input wire [11:0]load_data, output wire [7:0]opcode, output wire [3:0]instruction, operand);
  wire [11:0]address;
  Counter C1(clk, reset, load, enablec, load_data, address);
  ROM_Memory R1(address, opcode);
  Fetch F1(clk, reset, enablef, opcode, instruction, operand);
endmodule

Lab10/Codigo/Ejercicio1/Ejercicio1_tb.v
module testbench();
  //Variables de entrada
  reg clock, enablef, enablec, reset, load;
  reg [11:0]load_data;

  //Variables de salida
  wire [7:0]opcode;
  wire [3:0]instruction;
  wire [3:0]operand;

  //Instanciaciones
  Program P1(clock, reset, enablec, enablef, load, load_data, opcode, instruction, operand);

  always
    #1 clock <=~clock;

    //Ejercicio 1
    initial begin
    #2
    $display(" \nPrograma ");
    $display("clock reset enablec enablef load        load_data    |    opcode    instruction   operand ");
    $display("-----------------------------------------------------|------------------------------------");
    $monitor("%b       %b     %b       %b       %b       %b   |   %b      %b        %b", clock, reset, enablec, enablef, load, load_data, opcode, instruction, operand);

      enablec = 0; enablef = 0; reset = 1; clock = 0; load = 0; load_data = 12'b0;
  #2  enablec = 0; enablef = 0; reset = 0; load = 0; load_data = 12'b0;
  #2  enablec = 1; enablef = 1; reset = 0; load = 0; load_data = 12'b0;
  #6  enablec = 1; enablef = 1; reset = 0; load = 1; load_data = 12'b0;
  #2  enablec = 1; enablef = 1; reset = 0; load = 1; load_data = 12'b000000001010;
  #2  enablec = 1; enablef = 1; reset = 0; load = 0; load_data = 12'b0;
  #2  enablec = 1; enablef = 1; reset = 0; load = 0; load_data = 12'b0;
  #2  enablec = 1; enablef = 1; reset = 0; load = 0; load_data = 12'b0;
    end

    initial
      #18 $finish;
    initial begin
        $dumpfile("Ejercicio1_tb.vcd");
        $dumpvars(0, testbench);
      end
  endmodule

Lab10/Codigo/Ejercicio1/Ejercicio1_tb.vcd
$date
	Fri Nov 06 18:41:24 2020
$end
$version
	Icarus Verilog
$end
$timescale
	1ps
$end
$scope module testbench $end
$var wire 4 ! operand [3:0] $end
$var wire 8 " opcode [7:0] $end
$var wire 4 # instruction [3:0] $end
$var reg 1 $ clock $end
$var reg 1 % enablec $end
$var reg 1 & enablef $end
$var reg 1 ' load $end
$var reg 12 ( load_data [11:0] $end
$var reg 1 ) reset $end
$scope module P1 $end
$var wire 1 $ clk $end
$var wire 1 % enablec $end
$var wire 1 & enablef $end
$var wire 1 ' load $end
$var wire 12 * load_data [11:0] $end
$var wire 1 ) reset $end
$var wire 4 + operand [3:0] $end
$var wire 8 , opcode [7:0] $end
$var wire 4 - instruction [3:0] $end
$var wire 12 . address [11:0] $end
$scope module C1 $end
$var wire 1 $ clock $end
$var wire 1 % enable $end
$var wire 1 ' load $end
$var wire 12 / load_data [11:0] $end
$var wire 1 ) reset $end
$var reg 12 0 value [11:0] $end
$upscope $end
$scope module F1 $end
$var wire 1 $ clk $end
$var wire 1 & enable $end
$var wire 1 ) reset $end
$var wire 8 1 q [7:0] $end
$var wire 4 2 operand [3:0] $end
$var wire 8 3 opcode [7:0] $end
$var wire 4 4 instruction [3:0] $end
$scope module F1 $end
$var wire 1 $ clk $end
$var wire 1 & enable $end
$var wire 1 ) reset $end
$var wire 8 5 d [7:0] $end
$var reg 8 6 q [7:0] $end
$upscope $end
$upscope $end
$scope module R1 $end
$var wire 12 7 address [11:0] $end
$var wire 8 8 opcode [7:0] $end
$upscope $end
$upscope $end
$upscope $end
$enddefinitions $end
#0
$dumpvars
bx 8
bx 7
bx 6
bx 5
bx 4
bx 3
bx 2
bx 1
bx 0
bx /
bx .
bx -
bx ,
bx +
bx *
x)
bx (
x'
x&
x%
x$
bx #
bx "
bx !
$end
#2
b0 !
b0 +
b0 2
b0 #
b0 -
b0 4
b1000010 "
b1000010 ,
b1000010 3
b1000010 5
b1000010 8
b0 .
b0 0
b0 7
b0 1
b0 6
b0 (
b0 *
b0 /
0'
1$
1)
0&
0%
#3
0$
#4
1$
0)
#5
0$
#6
b0 "
b0 ,
b0 3
b0 5
b0 8
b1 .
b1 0
b1 7
b10 !
b10 +
b10 2
b100 #
b100 -
b100 4
b1000010 1
b1000010 6
1$
1&
1%
#7
0$
#8
b0 !
b0 +
b0 2
b0 #
b0 -
b0 4
b1111 "
b1111 ,
b1111 3
b1111 5
b1111 8
b10 .
b10 0
b10 7
b0 1
b0 6
1$
#9
0$
#10
b1111 !
b1111 +
b1111 2
b100 "
b100 ,
b100 3
b100 5
b100 8
b11 .
b11 0
b11 7
b1111 1
b1111 6
1$
#11
0$
#12
b10 !
b10 +
b10 2
b100 #
b100 -
b100 4
b1000010 1
b1000010 6
b1000010 "
b1000010 ,
b1000010 3
b1000010 5
b1000010 8
b0 .
b0 0
b0 7
1$
1'
#13
0$
#14
b0 !
b0 +
b0 2
b0 #
b0 -
b0 4
b0 1
b0 6
b0 "
b0 ,
b0 3
b0 5
b0 8
b1010 .
b1010 0
b1010 7
1$
b1010 (
b1010 *
b1010 /
#15
0$
#16
b101001 "
b101001 ,
b101001 3
b101001 5
b101001 8
b1100 .
b1100 0
b1100 7
1$
b0 (
b0 *
b0 /
0'
#17
0$
#18
b1001 !
b1001 +
b1001 2
b10 #
b10 -
b10 4
b11010101 "
b11010101 ,
b11010101 3
b11010101 5
b11010101 8
b1101 .
b1101 0
b1101 7
b101001 1
b101001 6
1$
