Lab10/Codigo/Ejercicio2/code.v
// Buffer Tri-estado --> Funciona
module Tris (input wire enable, input wire [3:0]in, output wire [3:0]out);
  assign out = enable ? in:4'bz;
endmodule

// Flip Flop Tipo D
module Accumulator (input wire clk, reset, enable, input wire [3:0]result, output reg [3:0]accu);
	always @ (posedge clk or posedge reset or enable) begin
		if (reset) begin
			accu <= 4'b0;
		end
    else if (enable) begin
      accu <= result;
    end
	end
endmodule

//ALU - Los 3 bits de seleccion vienen del microcode el databus es el operand y la accu es W
module ALU (input wire [3:0]data_bus, accu, input wire [2:0]selector, output wire [3:0]result, output wire [1:0]flags);
  wire zero, carry;
  reg [4:0]result_flags;
  always @ ( * ) begin
    case (selector)
    0:
      result_flags <= accu;
    1:
      result_flags <= accu - data_bus;
    2:
      result_flags <= data_bus;
    3:
      result_flags <= accu + data_bus;
    4:
      result_flags <= accu ~& data_bus;
    default:
      result_flags <= 5'b0;
    endcase
  end
  assign result = result_flags[3:0];
  assign carry = result_flags[4];
  assign zero = (result_flags == 5'b0) ? 1'b1:1'b0;
  assign flags[0] = zero;
  assign flags[1] = carry;
endmodule

module Program (input wire clk, reset, enablea, enablebuff1, enablebuff2, input wire [2:0]selector, input wire [3:0]in1, output wire [1:0]flags, output wire [3:0]out2);
  wire [3:0]data_bus, result, accu;
  Tris Buff1(enablebuff1, in1, data_bus);
  Accumulator W1(clk, reset, enablea, result, accu);
  ALU A1(data_bus, accu, selector, result, flags);
  Tris Buff2(enablebuff2, result, out2);
endmodule

Lab10/Codigo/Ejercicio2/code_tb.v
module testbench();
  //Variables de entrada
  reg clock, reset, enablea, enablebuff1, enablebuff2;
  reg [2:0]selector;
  reg [3:0]in;

  //Variables de salida
  wire [1:0]flags;
  wire [3:0]out, accu;

  //Instanciaciones
  Program P1(clock, reset, enablea, enablebuff1, enablebuff2, selector, in, flags, out);

  always
    #1 clock <=~clock;

    //Ejercicio 1
    initial begin
    #2
    $display(" \nPrograma ");
    $display("clock reset enablea enablebuff1 enablebuff2 selector    in   | flags   out ");
    $display("-------------------------------------------------------------|-------------");
    $monitor("%b       %b      %b          %b           %b       %b      %b  |  %b    %b ", clock, reset, enablea, enablebuff1, enablebuff2, selector, in, flags, out);

      enablea = 0; enablebuff1 = 0; enablebuff2 = 0; reset = 1; clock = 0; selector = 3'b0; in = 4'b0;
  #2  enablea = 0; enablebuff1 = 0; enablebuff2 = 0; reset = 0; selector = 3'b0; in = 4'b0;
  #2  enablea = 1; enablebuff1 = 1; enablebuff2 = 1; reset = 0; selector = 3'b0; in = 4'b1010;
  #2  enablea = 1; enablebuff1 = 1; enablebuff2 = 1; reset = 0; selector = 3'b001; in = 4'b0100;
  #2  enablea = 1; enablebuff1 = 1; enablebuff2 = 1; reset = 0; selector = 3'b010; in = 4'b0001;
  #2  enablea = 1; enablebuff1 = 1; enablebuff2 = 1; reset = 0; selector = 3'b011; in = 4'b0110;
  #2  enablea = 1; enablebuff1 = 1; enablebuff2 = 1; reset = 0; selector = 3'b100; in = 4'b0111;
    end

    initial
      #16 $finish;
    initial begin
        $dumpfile("code_tb.vcd");
        $dumpvars(0, testbench);
      end
  endmodule

Lab10/Codigo/Ejercicio2/code_tb.vcd
$date
	Fri Nov 06 21:52:25 2020
$end
$version
	Icarus Verilog
$end
$timescale
	1ps
$end
$scope module testbench $end
$var wire 4 ! out [3:0] $end
$var wire 2 " flags [1:0] $end
$var reg 1 # clock $end
$var reg 1 $ enablea $end
$var reg 1 % enablebuff1 $end
$var reg 1 & enablebuff2 $end
$var reg 4 ' in [3:0] $end
$var reg 1 ( reset $end
$var reg 3 ) selector [2:0] $end
$scope module P1 $end
$var wire 1 # clk $end
$var wire 1 $ enablea $end
$var wire 1 % enablebuff1 $end
$var wire 1 & enablebuff2 $end
$var wire 4 * in1 [3:0] $end
$var wire 1 ( reset $end
$var wire 3 + selector [2:0] $end
$var wire 4 , result [3:0] $end
$var wire 4 - out2 [3:0] $end
$var wire 2 . flags [1:0] $end
$var wire 4 / data_bus [3:0] $end
$var wire 4 0 accu [3:0] $end
$scope module A1 $end
$var wire 3 1 selector [2:0] $end
$var wire 1 2 zero $end
$var wire 4 3 result [3:0] $end
$var wire 2 4 flags [1:0] $end
$var wire 4 5 data_bus [3:0] $end
$var wire 1 6 carry $end
$var wire 4 7 accu [3:0] $end
$var reg 5 8 result_flags [4:0] $end
$upscope $end
$scope module Buff1 $end
$var wire 1 % enable $end
$var wire 4 9 in [3:0] $end
$var wire 4 : out [3:0] $end
$upscope $end
$scope module Buff2 $end
$var wire 1 & enable $end
$var wire 4 ; in [3:0] $end
$var wire 4 < out [3:0] $end
$upscope $end
$scope module W1 $end
$var wire 1 # clk $end
$var wire 1 $ enable $end
$var wire 1 ( reset $end
$var wire 4 = result [3:0] $end
$var reg 4 > accu [3:0] $end
$upscope $end
$upscope $end
$upscope $end
$enddefinitions $end
#0
$dumpvars
bx >
bx =
bx <
bx ;
bx :
bx 9
bx 8
bx 7
x6
bx 5
bx 4
bx 3
x2
bx 1
bx 0
bx /
bx .
bx -
bx ,
bx +
bx *
bx )
x(
bx '
x&
x%
x$
x#
bx "
bx !
$end
#2
b0 ,
b0 3
b0 ;
b0 =
12
b1 "
b1 .
b1 4
06
b0 8
b0 0
b0 7
b0 >
bz !
bz -
bz <
bz /
bz 5
bz :
b0 '
b0 *
b0 9
b0 )
b0 +
b0 1
1#
1(
0&
0%
0$
#3
0#
#4
1#
0(
#5
0#
#6
1#
b0 !
b0 -
b0 <
b1010 /
b1010 5
b1010 :
b1010 '
b1010 *
b1010 9
1&
1%
1$
#7
0#
#8
b1100 !
b1100 -
b1100 <
b1100 ,
b1100 3
b1100 ;
b1100 =
16
b10 "
b10 .
b10 4
02
b11100 8
1#
b100 /
b100 5
b100 :
b100 '
b100 *
b100 9
b1 )
b1 +
b1 1
#9
0#
#10
b1100 0
b1100 7
b1100 >
b1 !
b1 -
b1 <
b1 ,
b1 3
b1 ;
b1 =
b0 "
b0 .
b0 4
06
b1 8
1#
b1 /
b1 5
b1 :
b1 '
b1 *
b1 9
b10 )
b10 +
b10 1
#11
0#
#12
b1 0
b1 7
b1 >
b111 !
b111 -
b111 <
b0 "
b0 .
b0 4
06
b111 ,
b111 3
b111 ;
b111 =
b111 8
1#
b110 /
b110 5
b110 :
b110 '
b110 *
b110 9
b11 )
b11 +
b11 1
#13
0#
#14
b111 0
b111 7
b111 >
b1000 !
b1000 -
b1000 <
b1000 ,
b1000 3
b1000 ;
b1000 =
b10 "
b10 .
b10 4
16
b11000 8
1#
b111 /
b111 5
b111 :
b111 '
b111 *
b111 9
b100 )
b100 +
b100 1
#15
0#
#16
b1111 !
b1111 -
b1111 <
b1111 ,
b1111 3
b1111 ;
b1111 =
b11111 8
b1000 0
b1000 7
b1000 >
1#
