Lab6/code.v
//-----------------------------------
// Ricardo Pellecer Orellana
// Carné: 19072 = 0010 0101 0100 0000
// Bits menos significativos: 0100 0000
// 26/Agosto/2020
// Uso de multiplexores
// -----------------------------------


// Flip Flop de 4 entradas 

module flip_flop(input wire clk, reset, set,
				 input wire[3:0] d, 
				 output reg[3:0] q);	
	always @ (posedge clk or posedge reset or posedge set)begin
		if (reset) begin
			q <= 4'b0;
		end
		
		else if (set) begin
			q <= 4'b1111;
		end
		
		else begin
			q <= d;
		end
	end    
endmodule


// Flip Flop de 1 entradas 
module flip_flop_1(input wire clk, reset,
				 input wire d, 
				 output reg q);	
	always @ (posedge clk or posedge reset)begin
		if (reset) begin
			q <= 1'b0;
		end
		
		else begin
			q <= d;
		end
	end    
endmodule

module ejericio1(input wire A, B, clk, reset, 
				 output wire Y);	
	wire d1, d0, q1, q0;
	
	assign d0 = ~q0 & ~q1 & A;
	assign d1 = (q0 & B) | (q1 & A & B);
	
	assign Y = q1 & A & B; 
	
	flip_flop_1 F1(clk, reset, d1, q1);
	flip_flop_1 F0(clk, reset, d0, q0);
		
endmodule

module ejericio2(input wire A, clk, reset, 
				 output wire Y2, Y1, Y0);	
	wire d2, d1, d0, q2, q1, q0;
		
	assign d0 = ~q0;
	assign d1 = (~q1 & q0 & A) | (q1 & ~q0 & A) | (q1 & q0 & ~A) | (~q1 & ~q0 & ~A);
	assign d2 = (~q2 & q1 & q0 & A) | (~q2 & ~q1 & ~q0 & ~A) | (q2 & ~q1 & q0) | (q2 & ~q0 & A) | (q2 & q1 & ~A);
		
	flip_flop_1 F2(clk, reset, d2, q2);
	flip_flop_1 F1(clk, reset, d1, q1);
	flip_flop_1 F0(clk, reset, d0, q0);
	
	assign Y0 = q1 ^ q0; //(q1 & ~q0) + (~q1 & q0)
	assign Y1 = q1 ^ q2;
	assign Y2 = q2;	
	
	
endmodule

Lab6/test.v
// Esto es para aquellos que están usando iverilog de compilador
// Para los que usan apio pueden obviarlo
`include "code.v"
// ` -> backtick
// ' -> comilla simple


module testbench();

  // Inputs
  reg clk, reset, set;
  reg[3:0] d;
  wire[3:0] q;
  reg A, B, push;
  wire led1;
  wire led22, led21, led20;
  
  assign led2 = 3'b0; 
  
  always 
	  begin
		clk <= 0; #1 clk <= 1; #1; 
	  end
  
  flip_flop F1(clk, reset, set, d, q);
  ejericio1 E1(A, B, clk, reset, led1);
  ejericio2 E2(push, clk, reset, led22, led21, led20);
  
  
  always 
	  begin
		set <= 0; #1 set <= ~set; #3; 
	  end
	  
  
  initial begin
	#6
    $display("Flip Flop D - Reset Asincrono - Set Sincrono");
    $display("CLK SET  RESET     D    |   Q  ");
    $display("------------------------|------");
    $monitor(" %b    %b    %b     %b   | %b ", clk, set, reset, d, q);
		d[0] = 0; d[1] = 0; d[2] = 0; d[3] = 1; reset = 0;
	#1	d[0] = 0; d[1] = 1; d[2] = 1; d[3] = 0; reset = 0;
	#1	d[0] = 1; d[1] = 0; d[2] = 0; d[3] = 0; reset = 0;
	#1	d[0] = 0; d[1] = 0; d[2] = 1; d[3] = 1; reset = 0;
	#1	d[0] = 1; d[1] = 1; d[2] = 0; d[3] = 0; reset = 1;
	#1	d[0] = 1; d[1] = 1; d[2] = 1; d[3] = 0; reset = 0;
	#1	d[0] = 0; d[1] = 0; d[2] = 1; d[3] = 0; reset = 0;
	#1	d[0] = 0; d[1] = 1; d[2] = 0; d[3] = 1; reset = 0;
	#1	d[0] = 1; d[1] = 0; d[2] = 0; d[3] = 1; reset = 0;
	#1	d[0] = 1; d[1] = 1; d[2] = 0; d[3] = 1; reset = 1;
	#1	d[0] = 1; d[1] = 1; d[2] = 1; d[3] = 0; reset = 0;
	#1	d[0] = 0; d[1] = 1; d[2] = 1; d[3] = 1; reset = 1;
	#1	d[0] = 1; d[1] = 1; d[2] = 0; d[3] = 1; reset = 0;
	#1	d[0] = 1; d[1] = 1; d[2] = 0; d[3] = 0; reset = 0;
	#1	d[0] = 1; d[1] = 1; d[2] = 0; d[3] = 1; reset = 0;
	#1	d[0] = 1; d[1] = 0; d[2] = 0; d[3] = 0; reset = 0;
	end
  
  initial begin
  #22
    $display("Ejercicio 1");
    $display("A B | Y");
    $display("----|---");
    $monitor("%b %b | %b ", A, B, led1);
		A = 0; B = 0; 
	#2	A = 0; B = 1;
	#2	A = 1; B = 0;
	#2	A = 1; B = 1;
	#2	A = 0; B = 1;
	#2	A = 0; B = 0; 
	#2	A = 0; B = 1;
	#2	A = 1; B = 0;
	#2	A = 1; B = 1;
	#2	A = 0; B = 1;
	
	end
  
  initial begin
	#41
    $display("Ejercicio 3");
    $display(" Push |  Y2 Y1 Y0");
    $display("------|----------");
    $monitor("   %b  |  %b  %b  %b", push, led22, led21, led20);
		push = 0; reset = 1;
	#2	push = 0; reset = 0;
	#2  push = 0;
	#2  push = 0;
	#2  push = 0;
	#2  push = 0;
	#2  push = 0;
	#2  push = 0;
	#2  push = 1;
	#2  push = 1;
	#2  push = 1;
	#2  push = 1;
	#2  push = 1;
	#2  push = 1;
	#2  push = 1;
	#2  push = 1;
	
	end
  
  initial
    #73 $finish;
  
  initial begin
    $dumpfile("test_tb.vcd");
    $dumpvars(0, testbench);
  end
  
endmodule

Lab6/test_tb.vcd
$date
	Sat Sep 05 04:31:23 2020
$end
$version
	Icarus Verilog
$end
$timescale
	1s
$end
$scope module testbench $end
$var wire 1 ! led2 $end
$var wire 4 " q [3:0] $end
$var wire 1 # led22 $end
$var wire 1 $ led21 $end
$var wire 1 % led20 $end
$var wire 1 & led1 $end
$var reg 1 ' A $end
$var reg 1 ( B $end
$var reg 1 ) clk $end
$var reg 4 * d [3:0] $end
$var reg 1 + push $end
$var reg 1 , reset $end
$var reg 1 - set $end
$scope module E1 $end
$var wire 1 ' A $end
$var wire 1 ( B $end
$var wire 1 & Y $end
$var wire 1 ) clk $end
$var wire 1 . d0 $end
$var wire 1 / d1 $end
$var wire 1 , reset $end
$var wire 1 0 q1 $end
$var wire 1 1 q0 $end
$scope module F0 $end
$var wire 1 ) clk $end
$var wire 1 . d $end
$var wire 1 , reset $end
$var reg 1 1 q $end
$upscope $end
$scope module F1 $end
$var wire 1 ) clk $end
$var wire 1 / d $end
$var wire 1 , reset $end
$var reg 1 0 q $end
$upscope $end
$upscope $end
$scope module E2 $end
$var wire 1 + A $end
$var wire 1 % Y0 $end
$var wire 1 $ Y1 $end
$var wire 1 # Y2 $end
$var wire 1 ) clk $end
$var wire 1 2 d0 $end
$var wire 1 3 d1 $end
$var wire 1 4 d2 $end
$var wire 1 , reset $end
$var wire 1 5 q2 $end
$var wire 1 6 q1 $end
$var wire 1 7 q0 $end
$scope module F0 $end
$var wire 1 ) clk $end
$var wire 1 2 d $end
$var wire 1 , reset $end
$var reg 1 7 q $end
$upscope $end
$scope module F1 $end
$var wire 1 ) clk $end
$var wire 1 3 d $end
$var wire 1 , reset $end
$var reg 1 6 q $end
$upscope $end
$scope module F2 $end
$var wire 1 ) clk $end
$var wire 1 4 d $end
$var wire 1 , reset $end
$var reg 1 5 q $end
$upscope $end
$upscope $end
$scope module F1 $end
$var wire 1 ) clk $end
$var wire 4 8 d [3:0] $end
$var wire 1 , reset $end
$var wire 1 - set $end
$var reg 4 9 q [3:0] $end
$upscope $end
$upscope $end
$enddefinitions $end
#0
$dumpvars
bx 9
bx 8
x7
x6
x5
x4
x3
x2
x1
x0
x/
x.
0-
x,
x+
bx *
0)
x(
x'
x&
x%
x$
x#
bx "
0!
$end
#1
b1111 "
b1111 9
1-
1)
#2
0)
#3
1)
#4
0)
0-
#5
1)
1-
#6
0)
0,
b1000 *
b1000 8
#7
1)
b110 *
b110 8
#8
0)
0-
b1 *
b1 8
#9
1)
1-
b1100 *
b1100 8
#10
0/
0&
12
0%
0$
07
06
0#
05
01
00
b0 "
b0 9
0)
1,
b11 *
b11 8
#11
x/
x$
x%
02
x1
x#
x5
x6
17
b1111 "
b1111 9
1)
0,
b111 *
b111 8
#12
0)
0-
b100 *
b100 8
#13
x&
12
07
x0
1)
1-
b1010 *
b1010 8
#14
0)
b1001 *
b1001 8
#15
0/
0&
0$
0%
00
01
0#
05
06
b0 "
b0 9
1)
1,
b1011 *
b1011 8
#16
0)
0-
0,
b111 *
b111 8
#17
1)
1-
1,
b1110 *
b1110 8
#18
0)
0,
b1011 *
b1011 8
#19
x/
x$
x%
02
x1
x#
x5
x6
17
b1111 "
b1111 9
1)
b11 *
b11 8
#20
0)
0-
b1011 *
b1011 8
#21
x&
12
07
x0
1)
1-
b1 *
b1 8
#22
0)
0/
0&
0.
0(
0'
#23
02
00
01
17
1)
#24
0)
0-
1(
#25
12
07
1)
1-
#26
0)
1.
0(
1'
#27
0.
02
11
17
1)
#28
0)
0-
1/
1(
#29
1&
12
07
01
10
1)
1-
#30
0)
0/
0&
0'
#31
02
00
17
1)
#32
0)
0-
0(
#33
12
07
1)
1-
#34
0)
1(
#35
02
17
1)
#36
0)
0-
1.
0(
1'
#37
0.
12
07
11
1)
1-
#38
0)
1/
1(
#39
1&
1/
02
10
01
17
1)
#40
0)
0-
0/
0&
0'
#41
14
13
12
0%
0$
07
06
0#
05
00
b0 "
b0 9
1)
1-
1,
0+
#42
0)
#43
02
17
16
1#
15
b1111 "
b1111 9
1)
0,
#44
0)
0-
#45
03
1%
12
07
1)
1-
#46
0)
#47
14
02
1$
17
06
1)
#48
0)
0-
#49
04
13
0%
12
07
1)
1-
#50
0)
#51
02
17
16
0#
05
1)
#52
0)
0-
#53
03
1%
12
07
1)
1-
#54
0)
#55
02
0$
17
06
1)
#56
0)
0-
#57
1$
12
16
07
1)
1-
13
1+
#58
0)
#59
14
03
0%
02
17
1)
#60
0)
0-
#61
12
1#
15
06
07
1)
1-
#62
0)
#63
13
1%
02
17
1)
#64
0)
0-
#65
14
0$
12
16
07
1)
1-
#66
0)
#67
03
04
0%
02
17
1)
#68
0)
0-
#69
12
0#
05
06
07
1)
1-
#70
0)
#71
13
1%
02
17
1)
#72
0)
0-
#73
1$
12
16
07
1)
1-
