Lab9/Codigo/Ejercicio5/code.v
//-----------------------------------
// Ricardo Pellecer Orellana
// Carné: 19072
// 30/Octubre/2020
// -----------------------------------

// Ejercicio 5
// Código para Microcode
module Microcode(input wire [6:0]address, output reg [12:0]control);
  always @ ( * ) begin
    casex (address)
    7'bxxxxxx0: //0
      control <= 13'b1000000001000;
    7'b00001x1: //1
      control <= 13'b0100000001000;
    7'b00000x1: //2
      control <= 13'b1000000001000;
    7'b00011x1: //3
      control <= 13'b1000000001000;
    7'b00010x1: //4
      control <= 13'b0100000001000;
    7'b0010xx1: //5
      control <= 13'b0001001000010;
    7'b0011xx1: //6
      control <= 13'b1001001100000;
    7'b0100xx1: //7
      control <= 13'b0011010000010;
    7'b0101xx1: //8
      control <= 13'b0011010000100;
    7'b0110xx1: //9
      control <= 13'b1011010100000;
    7'b0111xx1: //10
      control <= 13'b1000000111000;
    7'b1000x11: //11
      control <= 13'b0100000001000;
    7'b1000x01: //12
      control <= 13'b1000000001000;
    7'b1001x11: //13
      control <= 13'b1000000001000;
    7'b1001x01: //14
      control <= 13'b0100000001000;
    7'b1010xx1: //15
      control <= 13'b0011011000010;
    7'b1011xx1: //16
      control <= 13'b1011011100000;
    7'b1100xx1: //17
      control <= 13'b0100000001000;
    7'b1101xx1: //18
      control <= 13'b0000000001001;
    7'b1110xx1: //19
      control <= 13'b0011100000010;
    7'b1111xx1: //20
      control <= 13'b1011100100000;
    default:
      control <= 13'b0;
    endcase
  end
endmodule

Lab9/Codigo/Ejercicio5/code_tb.v
module testbench();
  //Variables de entrada
  reg [6:0]address; //microcode

  //Variables de salida
  wire [12:0]control; //microcode

  //Instanciaciones
  Microcode MC(address, control);

    // Ejercicio 5
    initial begin
    #2
    $display(" \nMicrocode ");
    $display("address  |    control   ");
    $display("---------|-------------");
    $monitor("%b  | %b", address, control);

        address = 7'bxxxxxx0; //0
    #2  address = 7'b00001x1; //1
    #2  address = 7'b00000x1; //2
    #2  address = 7'b00011x1; //3
    #2  address = 7'b00010x1; //4
    #2  address = 7'b0010xx1; //5
    #2  address = 7'b0011xx1; //6
    #2  address = 7'b0100xx1; //7
    #2  address = 7'b0101xx1; //8
    #2  address = 7'b0110xx1; //9
    #2  address = 7'b0111xx1; //10
    #2  address = 7'b1000x11; //11
    #2  address = 7'b1000x01; //12
    #2  address = 7'b1001x11; //13
    #2  address = 7'b1001x01; //14
    #2  address = 7'b1010xx1; //15
    #2  address = 7'b1011xx1; //16
    #2  address = 7'b1100xx1; //17
    #2  address = 7'b1101xx1; //18
    #2  address = 7'b1110xx1; //19
    #2  address = 7'b1111xx1; //20

    #2  address = 7'b01000x1; //7
    #2  address = 7'b0101x11; //8
    #2  address = 7'b0110111; //9
    #2  address = 7'b0111001; //10
    #2  address = 7'b1000011; //11
    #2  address = 7'b1000101; //12
    #2  address = 7'b1001011; //13
    #2  address = 7'b1001101; //14
    end

    initial
      #60 $finish;
    initial begin
        $dumpfile("code_tb.vcd");
        $dumpvars(0, testbench);
      end
  endmodule

Lab9/Codigo/Ejercicio5/code_tb.vcd
$date
	Sat Oct 31 00:30:46 2020
$end
$version
	Icarus Verilog
$end
$timescale
	1ps
$end
$scope module testbench $end
$var wire 13 ! control [12:0] $end
$var reg 7 " address [6:0] $end
$scope module MC $end
$var wire 7 # address [6:0] $end
$var reg 13 $ control [12:0] $end
$upscope $end
$upscope $end
$enddefinitions $end
#0
$dumpvars
bx $
bx #
bx "
bx !
$end
#2
b1000000001000 !
b1000000001000 $
bx0 "
bx0 #
#4
b100000001000 !
b100000001000 $
b1x1 "
b1x1 #
#6
b1000000001000 !
b1000000001000 $
b0x1 "
b0x1 #
#8
b11x1 "
b11x1 #
#10
b100000001000 !
b100000001000 $
b10x1 "
b10x1 #
#12
b1001000010 !
b1001000010 $
b10xx1 "
b10xx1 #
#14
b1001001100000 !
b1001001100000 $
b11xx1 "
b11xx1 #
#16
b11010000010 !
b11010000010 $
b100xx1 "
b100xx1 #
#18
b11010000100 !
b11010000100 $
b101xx1 "
b101xx1 #
#20
b1011010100000 !
b1011010100000 $
b110xx1 "
b110xx1 #
#22
b1000000111000 !
b1000000111000 $
b111xx1 "
b111xx1 #
#24
b100000001000 !
b100000001000 $
b1000x11 "
b1000x11 #
#26
b1000000001000 !
b1000000001000 $
b1000x01 "
b1000x01 #
#28
b1001x11 "
b1001x11 #
#30
b100000001000 !
b100000001000 $
b1001x01 "
b1001x01 #
#32
b11011000010 !
b11011000010 $
b1010xx1 "
b1010xx1 #
#34
b1011011100000 !
b1011011100000 $
b1011xx1 "
b1011xx1 #
#36
b100000001000 !
b100000001000 $
b1100xx1 "
b1100xx1 #
#38
b1001 !
b1001 $
b1101xx1 "
b1101xx1 #
#40
b11100000010 !
b11100000010 $
b1110xx1 "
b1110xx1 #
#42
b1011100100000 !
b1011100100000 $
b1111xx1 "
b1111xx1 #
#44
b11010000010 !
b11010000010 $
b1000x1 "
b1000x1 #
#46
b11010000100 !
b11010000100 $
b101x11 "
b101x11 #
#48
b1011010100000 !
b1011010100000 $
b110111 "
b110111 #
#50
b1000000111000 !
b1000000111000 $
b111001 "
b111001 #
#52
b100000001000 !
b100000001000 $
b1000011 "
b1000011 #
#54
b1000000001000 !
b1000000001000 $
b1000101 "
b1000101 #
#56
b1001011 "
b1001011 #
#58
b100000001000 !
b100000001000 $
b1001101 "
b1001101 #
